{"$schema":"http://cyclonedx.org/schema/bom-1.6.schema.json","bomFormat":"CycloneDX","specVersion":"1.6","serialNumber":"urn:uuid:ac50d8e3-d9f8-45fb-92ec-81cc30001b96","version":1,"metadata":{"timestamp":"2026-04-20T18:29:49+02:00","tools":{"components":[{"type":"application","author":"anchore","name":"syft","version":"1.42.1"}]},"component":{"bom-ref":"fcd56ac316c53746","type":"file","name":"D:\\TFG\\Proyectosquesbomear\\jdonframework-master\\jdonframework-master"}},"components":[{"bom-ref":"pkg:maven/aopalliance/aopalliance@1.0?package-id=beed618a3ce06927","type":"library","name":"aopalliance","version":"1.0","cpe":"cpe:2.3:a:aopalliance:aopalliance:1.0:*:*:*:*:*:*:*","purl":"pkg:maven/aopalliance/aopalliance@1.0","externalReferences":[{"url":"","hashes":[{"alg":"SHA-1","content":"0235ba8b489512805ac13a8f9ea77a1ca5ebe3e8"}],"type":"build-meta"}],"properties":[{"name":"syft:package:foundBy","value":"java-archive-cataloger"},{"name":"syft:package:language","value":"java"},{"name":"syft:package:type","value":"java-archive"},{"name":"syft:package:metadataType","value":"java-archive"},{"name":"syft:location:0:path","value":"\\example\\cargo\\lib\\aopalliance-1.0.jar"},{"name":"syft:metadata:virtualPath","value":"\\example\\cargo\\lib\\aopalliance-1.0.jar"}]},{"bom-ref":"pkg:maven/aopalliance/aopalliance@1.0?package-id=2c98841528b61609","type":"library","group":"aopalliance","name":"aopalliance","version":"1.0","cpe":"cpe:2.3:a:aopalliance:aopalliance:1.0:*:*:*:*:*:*:*","purl":"pkg:maven/aopalliance/aopalliance@1.0","properties":[{"name":"syft:package:foundBy","value":"java-pom-cataloger"},{"name":"syft:package:language","value":"java"},{"name":"syft:package:type","value":"java-archive"},{"name":"syft:package:metadataType","value":"java-archive"},{"name":"syft:location:0:path","value":"\\pom.xml"},{"name":"syft:metadata:-:artifactID","value":"aopalliance"},{"name":"syft:metadata:-:groupID","value":"aopalliance"}]},{"bom-ref":"pkg:maven/cglib/cglib@2.2.2?package-id=1d8759a71cabdc61","type":"library","group":"cglib","name":"cglib","version":"2.2.2","cpe":"cpe:2.3:a:cglib:cglib:2.2.2:*:*:*:*:*:*:*","purl":"pkg:maven/cglib/cglib@2.2.2","properties":[{"name":"syft:package:foundBy","value":"java-pom-cataloger"},{"name":"syft:package:language","value":"java"},{"name":"syft:package:type","value":"java-archive"},{"name":"syft:package:metadataType","value":"java-archive"},{"name":"syft:location:0:path","value":"\\pom.xml"},{"name":"syft:metadata:-:artifactID","value":"cglib"},{"name":"syft:metadata:-:groupID","value":"cglib"}]},{"bom-ref":"pkg:maven/cglib/cglib@4.2.3.GA%20%28build%3A%20SVNTag%3DJBoss_4_2_3_GA%20date%3D200807181439%29?package-id=af2e5ec93d1cd8dd","type":"library","name":"cglib","version":"4.2.3.GA (build: SVNTag=JBoss_4_2_3_GA date=200807181439)","licenses":[{"license":{"id":"Apache-2.0"}}],"cpe":"cpe:2.3:a:jboss-\\(http\\:\\/\\/www-jboss-org\\/\\):cglib:4.2.3.GA_\\(build\\:_SVNTag\\=JBoss_4_2_3_GA_date\\=200807181439\\):*:*:*:*:*:*:*","purl":"pkg:maven/cglib/cglib@4.2.3.GA%20%28build%3A%20SVNTag%3DJBoss_4_2_3_GA%20date%3D200807181439%29","externalReferences":[{"url":"","hashes":[{"alg":"SHA-1","content":"676507b45d2db523adf930b31b52a4f06fff0c59"}],"type":"build-meta"}],"properties":[{"name":"syft:package:foundBy","value":"java-archive-cataloger"},{"name":"syft:package:language","value":"java"},{"name":"syft:package:type","value":"java-archive"},{"name":"syft:package:metadataType","value":"java-archive"},{"name":"syft:cpe23","value":"cpe:2.3:a:jboss_\\(http\\:\\/\\/www_jboss_org\\/\\):cglib:4.2.3.GA_\\(build\\:_SVNTag\\=JBoss_4_2_3_GA_date\\=200807181439\\):*:*:*:*:*:*:*"},{"name":"syft:cpe23","value":"cpe:2.3:a:jboss-inc-:cglib:4.2.3.GA_\\(build\\:_SVNTag\\=JBoss_4_2_3_GA_date\\=200807181439\\):*:*:*:*:*:*:*"},{"name":"syft:cpe23","value":"cpe:2.3:a:jboss_inc_:cglib:4.2.3.GA_\\(build\\:_SVNTag\\=JBoss_4_2_3_GA_date\\=200807181439\\):*:*:*:*:*:*:*"},{"name":"syft:cpe23","value":"cpe:2.3:a:cglib:cglib:4.2.3.GA_\\(build\\:_SVNTag\\=JBoss_4_2_3_GA_date\\=200807181439\\):*:*:*:*:*:*:*"},{"name":"syft:location:0:path","value":"\\example\\cargo\\lib\\cglib.jar"},{"name":"syft:metadata:virtualPath","value":"\\example\\cargo\\lib\\cglib.jar"}]},{"bom-ref":"pkg:maven/commons-beanutils/commons-beanutils@1.8.3?package-id=5f175b492c4ce13b","type":"library","group":"commons-beanutils","name":"commons-beanutils","version":"1.8.3","cpe":"cpe:2.3:a:commons-beanutils:commons-beanutils:1.8.3:*:*:*:*:*:*:*","purl":"pkg:maven/commons-beanutils/commons-beanutils@1.8.3","properties":[{"name":"syft:package:foundBy","value":"java-pom-cataloger"},{"name":"syft:package:language","value":"java"},{"name":"syft:package:type","value":"java-archive"},{"name":"syft:package:metadataType","value":"java-archive"},{"name":"syft:cpe23","value":"cpe:2.3:a:commons-beanutils:commons_beanutils:1.8.3:*:*:*:*:*:*:*"},{"name":"syft:cpe23","value":"cpe:2.3:a:commons_beanutils:commons-beanutils:1.8.3:*:*:*:*:*:*:*"},{"name":"syft:cpe23","value":"cpe:2.3:a:commons_beanutils:commons_beanutils:1.8.3:*:*:*:*:*:*:*"},{"name":"syft:cpe23","value":"cpe:2.3:a:commons:commons-beanutils:1.8.3:*:*:*:*:*:*:*"},{"name":"syft:cpe23","value":"cpe:2.3:a:commons:commons_beanutils:1.8.3:*:*:*:*:*:*:*"},{"name":"syft:location:0:path","value":"\\example\\jdonMVC+CQRS+ES\\pom.xml"},{"name":"syft:metadata:-:artifactID","value":"commons-beanutils"},{"name":"syft:metadata:-:groupID","value":"commons-beanutils"}]},{"bom-ref":"pkg:maven/commons-fileupload/commons-fileupload@1.2.2?package-id=729daa6dfde0e281","type":"library","group":"commons-fileupload","name":"commons-fileupload","version":"1.2.2","cpe":"cpe:2.3:a:commons-fileupload:commons-fileupload:1.2.2:*:*:*:*:*:*:*","purl":"pkg:maven/commons-fileupload/commons-fileupload@1.2.2","properties":[{"name":"syft:package:foundBy","value":"java-pom-cataloger"},{"name":"syft:package:language","value":"java"},{"name":"syft:package:type","value":"java-archive"},{"name":"syft:package:metadataType","value":"java-archive"},{"name":"syft:cpe23","value":"cpe:2.3:a:commons-fileupload:commons_fileupload:1.2.2:*:*:*:*:*:*:*"},{"name":"syft:cpe23","value":"cpe:2.3:a:commons_fileupload:commons-fileupload:1.2.2:*:*:*:*:*:*:*"},{"name":"syft:cpe23","value":"cpe:2.3:a:commons_fileupload:commons_fileupload:1.2.2:*:*:*:*:*:*:*"},{"name":"syft:cpe23","value":"cpe:2.3:a:commons:commons-fileupload:1.2.2:*:*:*:*:*:*:*"},{"name":"syft:cpe23","value":"cpe:2.3:a:commons:commons_fileupload:1.2.2:*:*:*:*:*:*:*"},{"name":"syft:location:0:path","value":"\\example\\jdonMVC+CQRS+ES\\pom.xml"},{"name":"syft:metadata:-:artifactID","value":"commons-fileupload"},{"name":"syft:metadata:-:groupID","value":"commons-fileupload"}]},{"bom-ref":"pkg:maven/org.apache.commons/commons-io@1.3.2?package-id=807092dd4b0394f6","type":"library","group":"org.apache.commons","name":"commons-io","version":"1.3.2","cpe":"cpe:2.3:a:apache:commons-io:1.3.2:*:*:*:*:*:*:*","purl":"pkg:maven/org.apache.commons/commons-io@1.3.2","properties":[{"name":"syft:package:foundBy","value":"java-pom-cataloger"},{"name":"syft:package:language","value":"java"},{"name":"syft:package:type","value":"java-archive"},{"name":"syft:package:metadataType","value":"java-archive"},{"name":"syft:cpe23","value":"cpe:2.3:a:apache:commons_io:1.3.2:*:*:*:*:*:*:*"},{"name":"syft:cpe23","value":"cpe:2.3:a:apache:commons:1.3.2:*:*:*:*:*:*:*"},{"name":"syft:location:0:path","value":"\\example\\jdonMVC+CQRS+ES\\pom.xml"},{"name":"syft:metadata:-:artifactID","value":"commons-io"},{"name":"syft:metadata:-:groupID","value":"org.apache.commons"}]},{"bom-ref":"pkg:maven/commons-logging/commons-logging@1.1.1?package-id=131de380abb2c5cf","type":"library","group":"commons-logging","name":"commons-logging","version":"1.1.1","cpe":"cpe:2.3:a:commons-logging:commons-logging:1.1.1:*:*:*:*:*:*:*","purl":"pkg:maven/commons-logging/commons-logging@1.1.1","properties":[{"name":"syft:package:foundBy","value":"java-pom-cataloger"},{"name":"syft:package:language","value":"java"},{"name":"syft:package:type","value":"java-archive"},{"name":"syft:package:metadataType","value":"java-archive"},{"name":"syft:cpe23","value":"cpe:2.3:a:commons-logging:commons_logging:1.1.1:*:*:*:*:*:*:*"},{"name":"syft:cpe23","value":"cpe:2.3:a:commons_logging:commons-logging:1.1.1:*:*:*:*:*:*:*"},{"name":"syft:cpe23","value":"cpe:2.3:a:commons_logging:commons_logging:1.1.1:*:*:*:*:*:*:*"},{"name":"syft:cpe23","value":"cpe:2.3:a:commons:commons-logging:1.1.1:*:*:*:*:*:*:*"},{"name":"syft:cpe23","value":"cpe:2.3:a:commons:commons_logging:1.1.1:*:*:*:*:*:*:*"},{"name":"syft:location:0:path","value":"\\example\\jdonMVC+CQRS+ES\\pom.xml"},{"name":"syft:metadata:-:artifactID","value":"commons-logging"},{"name":"syft:metadata:-:groupID","value":"commons-logging"}]},{"bom-ref":"pkg:maven/commons-pool/commons-pool@1.5.1?package-id=7f800d06495a8d28","type":"library","group":"commons-pool","name":"commons-pool","version":"1.5.1","licenses":[{"license":{"id":"Apache-2.0"}}],"cpe":"cpe:2.3:a:apache:commons-pool:1.5.1:*:*:*:*:*:*:*","purl":"pkg:maven/commons-pool/commons-pool@1.5.1","externalReferences":[{"url":"","hashes":[{"alg":"SHA-1","content":"08e517b8b9250319a58a163baac51d2ba632e458"}],"type":"build-meta"}],"properties":[{"name":"syft:package:foundBy","value":"java-archive-cataloger"},{"name":"syft:package:language","value":"java"},{"name":"syft:package:type","value":"java-archive"},{"name":"syft:package:metadataType","value":"java-archive"},{"name":"syft:cpe23","value":"cpe:2.3:a:apache:commons_pool:1.5.1:*:*:*:*:*:*:*"},{"name":"syft:cpe23","value":"cpe:2.3:a:apache:commons:1.5.1:*:*:*:*:*:*:*"},{"name":"syft:cpe23","value":"cpe:2.3:a:apache:pool:1.5.1:*:*:*:*:*:*:*"},{"name":"syft:location:0:path","value":"\\example\\cargo\\lib\\commons-pool-1.5.1.jar"},{"name":"syft:metadata:-:artifactID","value":"commons-pool"},{"name":"syft:metadata:-:groupID","value":"commons-pool"},{"name":"syft:metadata:virtualPath","value":"\\example\\cargo\\lib\\commons-pool-1.5.1.jar"}]},{"bom-ref":"pkg:maven/commons-pool/commons-pool@1.6?package-id=610cee33174f21fc","type":"library","group":"commons-pool","name":"commons-pool","version":"1.6","cpe":"cpe:2.3:a:commons-pool:commons-pool:1.6:*:*:*:*:*:*:*","purl":"pkg:maven/commons-pool/commons-pool@1.6","properties":[{"name":"syft:package:foundBy","value":"java-pom-cataloger"},{"name":"syft:package:language","value":"java"},{"name":"syft:package:type","value":"java-archive"},{"name":"syft:package:metadataType","value":"java-archive"},{"name":"syft:cpe23","value":"cpe:2.3:a:commons-pool:commons_pool:1.6:*:*:*:*:*:*:*"},{"name":"syft:cpe23","value":"cpe:2.3:a:commons_pool:commons-pool:1.6:*:*:*:*:*:*:*"},{"name":"syft:cpe23","value":"cpe:2.3:a:commons_pool:commons_pool:1.6:*:*:*:*:*:*:*"},{"name":"syft:cpe23","value":"cpe:2.3:a:commons:commons-pool:1.6:*:*:*:*:*:*:*"},{"name":"syft:cpe23","value":"cpe:2.3:a:commons:commons_pool:1.6:*:*:*:*:*:*:*"},{"name":"syft:location:0:path","value":"\\example\\cqrs+dci\\robot\\pom.xml"},{"name":"syft:metadata:-:artifactID","value":"commons-pool"},{"name":"syft:metadata:-:groupID","value":"commons-pool"}]},{"bom-ref":"pkg:maven/org.commontemplate/commontemplate@0.8.7?package-id=ab2c0ef5b5060487","type":"library","group":"org.commontemplate","name":"commontemplate","version":"0.8.7","cpe":"cpe:2.3:a:org.commontemplate:commontemplate:0.8.7:*:*:*:*:*:*:*","purl":"pkg:maven/org.commontemplate/commontemplate@0.8.7","properties":[{"name":"syft:package:foundBy","value":"java-pom-cataloger"},{"name":"syft:package:language","value":"java"},{"name":"syft:package:type","value":"java-archive"},{"name":"syft:package:metadataType","value":"java-archive"},{"name":"syft:cpe23","value":"cpe:2.3:a:commontemplate:commontemplate:0.8.7:*:*:*:*:*:*:*"},{"name":"syft:location:0:path","value":"\\example\\jdonMVC+CQRS+ES\\pom.xml"},{"name":"syft:metadata:-:artifactID","value":"commontemplate"},{"name":"syft:metadata:-:groupID","value":"org.commontemplate"}]},{"bom-ref":"pkg:maven/sample/dciderobot@1.0-SNAPSHOT?package-id=c767a110c900f67c","type":"library","name":"dciderobot","version":"1.0-SNAPSHOT","cpe":"cpe:2.3:a:dciderobot:dciderobot:1.0-SNAPSHOT:*:*:*:*:*:*:*","purl":"pkg:maven/sample/dciderobot@1.0-SNAPSHOT","properties":[{"name":"syft:package:foundBy","value":"java-pom-cataloger"},{"name":"syft:package:language","value":"java"},{"name":"syft:package:type","value":"java-archive"},{"name":"syft:package:metadataType","value":"java-archive"},{"name":"syft:location:0:path","value":"\\example\\dci+de\\robot\\pom.xml"}]},{"bom-ref":"pkg:maven/disruptor/disruptor@2.8?package-id=e01ac2746704cd68","type":"library","name":"disruptor","version":"2.8","cpe":"cpe:2.3:a:disruptor:disruptor:2.8:*:*:*:*:*:*:*","purl":"pkg:maven/disruptor/disruptor@2.8","externalReferences":[{"url":"","hashes":[{"alg":"SHA-1","content":"dd22989e040b12628eeee369a21e6604612c5072"}],"type":"build-meta"}],"properties":[{"name":"syft:package:foundBy","value":"java-archive-cataloger"},{"name":"syft:package:language","value":"java"},{"name":"syft:package:type","value":"java-archive"},{"name":"syft:package:metadataType","value":"java-archive"},{"name":"syft:location:0:path","value":"\\example\\cargo\\lib\\disruptor-2.8.jar"},{"name":"syft:metadata:virtualPath","value":"\\example\\cargo\\lib\\disruptor-2.8.jar"}]},{"bom-ref":"pkg:maven/com.lmax/disruptor@3.3.8?package-id=36812b404a8a534a","type":"library","group":"com.lmax","name":"disruptor","version":"3.3.8","cpe":"cpe:2.3:a:disruptor:disruptor:3.3.8:*:*:*:*:*:*:*","purl":"pkg:maven/com.lmax/disruptor@3.3.8","properties":[{"name":"syft:package:foundBy","value":"java-pom-cataloger"},{"name":"syft:package:language","value":"java"},{"name":"syft:package:type","value":"java-archive"},{"name":"syft:package:metadataType","value":"java-archive"},{"name":"syft:cpe23","value":"cpe:2.3:a:com.lmax:disruptor:3.3.8:*:*:*:*:*:*:*"},{"name":"syft:cpe23","value":"cpe:2.3:a:lmax:disruptor:3.3.8:*:*:*:*:*:*:*"},{"name":"syft:location:0:path","value":"\\pom.xml"},{"name":"syft:metadata:-:artifactID","value":"disruptor"},{"name":"syft:metadata:-:groupID","value":"com.lmax"}]},{"bom-ref":"pkg:maven/net.sf.ehcache/ehcache@1.6.2?package-id=b0136da7589c5d1d","type":"library","group":"net.sf.ehcache","name":"ehcache","version":"1.6.2","cpe":"cpe:2.3:a:net.sf.ehcache:ehcache:1.6.2:*:*:*:*:*:*:*","purl":"pkg:maven/net.sf.ehcache/ehcache@1.6.2","externalReferences":[{"url":"","hashes":[{"alg":"SHA-1","content":"4c7ef0497c5c8d098f43cb347f346cbc0b042ecd"}],"type":"build-meta"}],"properties":[{"name":"syft:package:foundBy","value":"java-archive-cataloger"},{"name":"syft:package:language","value":"java"},{"name":"syft:package:type","value":"java-archive"},{"name":"syft:package:metadataType","value":"java-archive"},{"name":"syft:cpe23","value":"cpe:2.3:a:ehcache:ehcache:1.6.2:*:*:*:*:*:*:*"},{"name":"syft:cpe23","value":"cpe:2.3:a:sf:ehcache:1.6.2:*:*:*:*:*:*:*"},{"name":"syft:location:0:path","value":"\\example\\cargo\\lib\\ehcache-1.6.2.jar"},{"name":"syft:metadata:-:artifactID","value":"ehcache"},{"name":"syft:metadata:-:groupID","value":"net.sf.ehcache"},{"name":"syft:metadata:virtualPath","value":"\\example\\cargo\\lib\\ehcache-1.6.2.jar"}]},{"bom-ref":"pkg:maven/freemarker/freemarker@2.3.8?package-id=c2bf22f3c2ec5934","type":"library","group":"freemarker","name":"freemarker","version":"2.3.8","cpe":"cpe:2.3:a:freemarker:freemarker:2.3.8:*:*:*:*:*:*:*","purl":"pkg:maven/freemarker/freemarker@2.3.8","properties":[{"name":"syft:package:foundBy","value":"java-pom-cataloger"},{"name":"syft:package:language","value":"java"},{"name":"syft:package:type","value":"java-archive"},{"name":"syft:package:metadataType","value":"java-archive"},{"name":"syft:location:0:path","value":"\\example\\jdonMVC+CQRS+ES\\pom.xml"},{"name":"syft:metadata:-:artifactID","value":"freemarker"},{"name":"syft:metadata:-:groupID","value":"freemarker"}]},{"bom-ref":"pkg:maven/gradle-wrapper/gradle-wrapper@1.8?package-id=0065bae32cbdadfa","type":"library","name":"gradle-wrapper","version":"1.8","cpe":"cpe:2.3:a:gradle-wrapper:gradle-wrapper:1.8:*:*:*:*:*:*:*","purl":"pkg:maven/gradle-wrapper/gradle-wrapper@1.8","externalReferences":[{"url":"","hashes":[{"alg":"SHA-1","content":"0d7b175883ea576543d3dbfee42894b103cf35c1"}],"type":"build-meta"}],"properties":[{"name":"syft:package:foundBy","value":"java-archive-cataloger"},{"name":"syft:package:language","value":"java"},{"name":"syft:package:type","value":"java-archive"},{"name":"syft:package:metadataType","value":"java-archive"},{"name":"syft:cpe23","value":"cpe:2.3:a:gradle-wrapper:gradle_wrapper:1.8:*:*:*:*:*:*:*"},{"name":"syft:cpe23","value":"cpe:2.3:a:gradle_wrapper:gradle-wrapper:1.8:*:*:*:*:*:*:*"},{"name":"syft:cpe23","value":"cpe:2.3:a:gradle_wrapper:gradle_wrapper:1.8:*:*:*:*:*:*:*"},{"name":"syft:cpe23","value":"cpe:2.3:a:gradle:gradle-wrapper:1.8:*:*:*:*:*:*:*"},{"name":"syft:cpe23","value":"cpe:2.3:a:gradle:gradle_wrapper:1.8:*:*:*:*:*:*:*"},{"name":"syft:location:0:path","value":"\\example\\jdonMVC+CQRS+ES\\gradle\\wrapper\\gradle-wrapper.jar"},{"name":"syft:metadata:virtualPath","value":"\\example\\jdonMVC+CQRS+ES\\gradle\\wrapper\\gradle-wrapper.jar"}]},{"bom-ref":"pkg:maven/com.google.guava/guava@23.0?package-id=a57443ee8defe627","type":"library","group":"com.google.guava","name":"guava","version":"23.0","cpe":"cpe:2.3:a:com.google.guava:guava:23.0:*:*:*:*:*:*:*","purl":"pkg:maven/com.google.guava/guava@23.0","properties":[{"name":"syft:package:foundBy","value":"java-pom-cataloger"},{"name":"syft:package:language","value":"java"},{"name":"syft:package:type","value":"java-archive"},{"name":"syft:package:metadataType","value":"java-archive"},{"name":"syft:cpe23","value":"cpe:2.3:a:google:guava:23.0:*:*:*:*:*:*:*"},{"name":"syft:cpe23","value":"cpe:2.3:a:guava:guava:23.0:*:*:*:*:*:*:*"},{"name":"syft:location:0:path","value":"\\pom.xml"},{"name":"syft:metadata:-:artifactID","value":"guava"},{"name":"syft:metadata:-:groupID","value":"com.google.guava"}]},{"bom-ref":"pkg:maven/org.javassist/javassist@3.23.1-GA?package-id=275e430d9b8ec171","type":"library","group":"org.javassist","name":"javassist","version":"3.23.1-GA","cpe":"cpe:2.3:a:org.javassist:javassist:3.23.1-GA:*:*:*:*:*:*:*","purl":"pkg:maven/org.javassist/javassist@3.23.1-GA","properties":[{"name":"syft:package:foundBy","value":"java-pom-cataloger"},{"name":"syft:package:language","value":"java"},{"name":"syft:package:type","value":"java-archive"},{"name":"syft:package:metadataType","value":"java-archive"},{"name":"syft:cpe23","value":"cpe:2.3:a:javassist:javassist:3.23.1-GA:*:*:*:*:*:*:*"},{"name":"syft:location:0:path","value":"\\pom.xml"},{"name":"syft:metadata:-:artifactID","value":"javassist"},{"name":"syft:metadata:-:groupID","value":"org.javassist"}]},{"bom-ref":"pkg:maven/jdom/jdom@1.0?package-id=14abf15ec06f3b49","type":"library","group":"jdom","name":"jdom","version":"1.0","cpe":"cpe:2.3:a:jdom:jdom:1.0:*:*:*:*:*:*:*","purl":"pkg:maven/jdom/jdom@1.0","properties":[{"name":"syft:package:foundBy","value":"java-pom-cataloger"},{"name":"syft:package:language","value":"java"},{"name":"syft:package:type","value":"java-archive"},{"name":"syft:package:metadataType","value":"java-archive"},{"name":"syft:location:0:path","value":"\\JdonAccessory\\jdon-hibernate3x\\pom.xml"},{"name":"syft:metadata:-:artifactID","value":"jdom"},{"name":"syft:metadata:-:groupID","value":"jdom"}]},{"bom-ref":"pkg:maven/org.jdom/jdom@1.0?package-id=5832a3a7de5d3c59","type":"library","name":"jdom","version":"1.0","licenses":[{"license":{"name":"sha256:f076dd293ead5fe67bc39b220e06b128ac37d17ce13f62d14a07d4ef08f766bc"}}],"cpe":"cpe:2.3:a:org.jdom.transform:transform:1.0:*:*:*:*:*:*:*","purl":"pkg:maven/org.jdom/jdom@1.0","externalReferences":[{"url":"","hashes":[{"alg":"SHA-1","content":"a2ac1cd690ab4c80defe7f9bce14d35934c35cec"}],"type":"build-meta"}],"properties":[{"name":"syft:package:foundBy","value":"java-archive-cataloger"},{"name":"syft:package:language","value":"java"},{"name":"syft:package:type","value":"java-archive"},{"name":"syft:package:metadataType","value":"java-archive"},{"name":"syft:cpe23","value":"cpe:2.3:a:org.jdom.adapters:transform:1.0:*:*:*:*:*:*:*"},{"name":"syft:cpe23","value":"cpe:2.3:a:org.jdom.transform:adapters:1.0:*:*:*:*:*:*:*"},{"name":"syft:cpe23","value":"cpe:2.3:a:org.jdom.adapters:adapters:1.0:*:*:*:*:*:*:*"},{"name":"syft:cpe23","value":"cpe:2.3:a:org.jdom.filter:transform:1.0:*:*:*:*:*:*:*"},{"name":"syft:cpe23","value":"cpe:2.3:a:org.jdom.output:transform:1.0:*:*:*:*:*:*:*"},{"name":"syft:cpe23","value":"cpe:2.3:a:org.jdom.transform:filter:1.0:*:*:*:*:*:*:*"},{"name":"syft:cpe23","value":"cpe:2.3:a:org.jdom.transform:output:1.0:*:*:*:*:*:*:*"},{"name":"syft:cpe23","value":"cpe:2.3:a:org.jdom.adapters:filter:1.0:*:*:*:*:*:*:*"},{"name":"syft:cpe23","value":"cpe:2.3:a:org.jdom.adapters:output:1.0:*:*:*:*:*:*:*"},{"name":"syft:cpe23","value":"cpe:2.3:a:org.jdom.filter:adapters:1.0:*:*:*:*:*:*:*"},{"name":"syft:cpe23","value":"cpe:2.3:a:org.jdom.input:transform:1.0:*:*:*:*:*:*:*"},{"name":"syft:cpe23","value":"cpe:2.3:a:org.jdom.output:adapters:1.0:*:*:*:*:*:*:*"},{"name":"syft:cpe23","value":"cpe:2.3:a:org.jdom.transform:input:1.0:*:*:*:*:*:*:*"},{"name":"syft:cpe23","value":"cpe:2.3:a:org.jdom.transform:xpath:1.0:*:*:*:*:*:*:*"},{"name":"syft:cpe23","value":"cpe:2.3:a:org.jdom.xpath:transform:1.0:*:*:*:*:*:*:*"},{"name":"syft:cpe23","value":"cpe:2.3:a:org.jdom.adapters:input:1.0:*:*:*:*:*:*:*"},{"name":"syft:cpe23","value":"cpe:2.3:a:org.jdom.adapters:xpath:1.0:*:*:*:*:*:*:*"},{"name":"syft:cpe23","value":"cpe:2.3:a:org.jdom.input:adapters:1.0:*:*:*:*:*:*:*"},{"name":"syft:cpe23","value":"cpe:2.3:a:org.jdom.transform:jdom:1.0:*:*:*:*:*:*:*"},{"name":"syft:cpe23","value":"cpe:2.3:a:org.jdom.xpath:adapters:1.0:*:*:*:*:*:*:*"},{"name":"syft:cpe23","value":"cpe:2.3:a:org.jdom.adapters:jdom:1.0:*:*:*:*:*:*:*"},{"name":"syft:cpe23","value":"cpe:2.3:a:org.jdom.filter:filter:1.0:*:*:*:*:*:*:*"},{"name":"syft:cpe23","value":"cpe:2.3:a:org.jdom.filter:output:1.0:*:*:*:*:*:*:*"},{"name":"syft:cpe23","value":"cpe:2.3:a:org.jdom.output:filter:1.0:*:*:*:*:*:*:*"},{"name":"syft:cpe23","value":"cpe:2.3:a:org.jdom.output:output:1.0:*:*:*:*:*:*:*"},{"name":"syft:cpe23","value":"cpe:2.3:a:org.jdom.filter:input:1.0:*:*:*:*:*:*:*"},{"name":"syft:cpe23","value":"cpe:2.3:a:org.jdom.filter:xpath:1.0:*:*:*:*:*:*:*"},{"name":"syft:cpe23","value":"cpe:2.3:a:org.jdom.input:filter:1.0:*:*:*:*:*:*:*"},{"name":"syft:cpe23","value":"cpe:2.3:a:org.jdom.input:output:1.0:*:*:*:*:*:*:*"},{"name":"syft:cpe23","value":"cpe:2.3:a:org.jdom.output:input:1.0:*:*:*:*:*:*:*"},{"name":"syft:cpe23","value":"cpe:2.3:a:org.jdom.output:xpath:1.0:*:*:*:*:*:*:*"},{"name":"syft:cpe23","value":"cpe:2.3:a:org.jdom.xpath:filter:1.0:*:*:*:*:*:*:*"},{"name":"syft:cpe23","value":"cpe:2.3:a:org.jdom.xpath:output:1.0:*:*:*:*:*:*:*"},{"name":"syft:cpe23","value":"cpe:2.3:a:org.jdom.filter:jdom:1.0:*:*:*:*:*:*:*"},{"name":"syft:cpe23","value":"cpe:2.3:a:org.jdom.input:input:1.0:*:*:*:*:*:*:*"},{"name":"syft:cpe23","value":"cpe:2.3:a:org.jdom.input:xpath:1.0:*:*:*:*:*:*:*"},{"name":"syft:cpe23","value":"cpe:2.3:a:org.jdom.output:jdom:1.0:*:*:*:*:*:*:*"},{"name":"syft:cpe23","value":"cpe:2.3:a:org.jdom.xpath:input:1.0:*:*:*:*:*:*:*"},{"name":"syft:cpe23","value":"cpe:2.3:a:org.jdom.xpath:xpath:1.0:*:*:*:*:*:*:*"},{"name":"syft:cpe23","value":"cpe:2.3:a:org.jdom.input:jdom:1.0:*:*:*:*:*:*:*"},{"name":"syft:cpe23","value":"cpe:2.3:a:org.jdom.xpath:jdom:1.0:*:*:*:*:*:*:*"},{"name":"syft:cpe23","value":"cpe:2.3:a:transform:transform:1.0:*:*:*:*:*:*:*"},{"name":"syft:cpe23","value":"cpe:2.3:a:adapters:transform:1.0:*:*:*:*:*:*:*"},{"name":"syft:cpe23","value":"cpe:2.3:a:jdom-org:transform:1.0:*:*:*:*:*:*:*"},{"name":"syft:cpe23","value":"cpe:2.3:a:jdom_org:transform:1.0:*:*:*:*:*:*:*"},{"name":"syft:cpe23","value":"cpe:2.3:a:org.jdom:transform:1.0:*:*:*:*:*:*:*"},{"name":"syft:cpe23","value":"cpe:2.3:a:transform:adapters:1.0:*:*:*:*:*:*:*"},{"name":"syft:cpe23","value":"cpe:2.3:a:adapters:adapters:1.0:*:*:*:*:*:*:*"},{"name":"syft:cpe23","value":"cpe:2.3:a:jdom-org:adapters:1.0:*:*:*:*:*:*:*"},{"name":"syft:cpe23","value":"cpe:2.3:a:jdom_org:adapters:1.0:*:*:*:*:*:*:*"},{"name":"syft:cpe23","value":"cpe:2.3:a:org.jdom:adapters:1.0:*:*:*:*:*:*:*"},{"name":"syft:cpe23","value":"cpe:2.3:a:filter:transform:1.0:*:*:*:*:*:*:*"},{"name":"syft:cpe23","value":"cpe:2.3:a:output:transform:1.0:*:*:*:*:*:*:*"},{"name":"syft:cpe23","value":"cpe:2.3:a:transform:filter:1.0:*:*:*:*:*:*:*"},{"name":"syft:cpe23","value":"cpe:2.3:a:transform:output:1.0:*:*:*:*:*:*:*"},{"name":"syft:cpe23","value":"cpe:2.3:a:adapters:filter:1.0:*:*:*:*:*:*:*"},{"name":"syft:cpe23","value":"cpe:2.3:a:adapters:output:1.0:*:*:*:*:*:*:*"},{"name":"syft:cpe23","value":"cpe:2.3:a:filter:adapters:1.0:*:*:*:*:*:*:*"},{"name":"syft:cpe23","value":"cpe:2.3:a:input:transform:1.0:*:*:*:*:*:*:*"},{"name":"syft:cpe23","value":"cpe:2.3:a:jdom-org:filter:1.0:*:*:*:*:*:*:*"},{"name":"syft:cpe23","value":"cpe:2.3:a:jdom-org:output:1.0:*:*:*:*:*:*:*"},{"name":"syft:cpe23","value":"cpe:2.3:a:jdom_org:filter:1.0:*:*:*:*:*:*:*"},{"name":"syft:cpe23","value":"cpe:2.3:a:jdom_org:output:1.0:*:*:*:*:*:*:*"},{"name":"syft:cpe23","value":"cpe:2.3:a:org.jdom:filter:1.0:*:*:*:*:*:*:*"},{"name":"syft:cpe23","value":"cpe:2.3:a:org.jdom:output:1.0:*:*:*:*:*:*:*"},{"name":"syft:cpe23","value":"cpe:2.3:a:output:adapters:1.0:*:*:*:*:*:*:*"},{"name":"syft:cpe23","value":"cpe:2.3:a:transform:input:1.0:*:*:*:*:*:*:*"},{"name":"syft:cpe23","value":"cpe:2.3:a:transform:xpath:1.0:*:*:*:*:*:*:*"},{"name":"syft:cpe23","value":"cpe:2.3:a:xpath:transform:1.0:*:*:*:*:*:*:*"},{"name":"syft:cpe23","value":"cpe:2.3:a:adapters:input:1.0:*:*:*:*:*:*:*"},{"name":"syft:cpe23","value":"cpe:2.3:a:adapters:xpath:1.0:*:*:*:*:*:*:*"},{"name":"syft:cpe23","value":"cpe:2.3:a:input:adapters:1.0:*:*:*:*:*:*:*"},{"name":"syft:cpe23","value":"cpe:2.3:a:jdom-org:input:1.0:*:*:*:*:*:*:*"},{"name":"syft:cpe23","value":"cpe:2.3:a:jdom-org:xpath:1.0:*:*:*:*:*:*:*"},{"name":"syft:cpe23","value":"cpe:2.3:a:jdom:transform:1.0:*:*:*:*:*:*:*"},{"name":"syft:cpe23","value":"cpe:2.3:a:jdom_org:input:1.0:*:*:*:*:*:*:*"},{"name":"syft:cpe23","value":"cpe:2.3:a:jdom_org:xpath:1.0:*:*:*:*:*:*:*"},{"name":"syft:cpe23","value":"cpe:2.3:a:org.jdom:input:1.0:*:*:*:*:*:*:*"},{"name":"syft:cpe23","value":"cpe:2.3:a:org.jdom:xpath:1.0:*:*:*:*:*:*:*"},{"name":"syft:cpe23","value":"cpe:2.3:a:transform:jdom:1.0:*:*:*:*:*:*:*"},{"name":"syft:cpe23","value":"cpe:2.3:a:xpath:adapters:1.0:*:*:*:*:*:*:*"},{"name":"syft:cpe23","value":"cpe:2.3:a:adapters:jdom:1.0:*:*:*:*:*:*:*"},{"name":"syft:cpe23","value":"cpe:2.3:a:filter:filter:1.0:*:*:*:*:*:*:*"},{"name":"syft:cpe23","value":"cpe:2.3:a:filter:output:1.0:*:*:*:*:*:*:*"},{"name":"syft:cpe23","value":"cpe:2.3:a:jdom-org:jdom:1.0:*:*:*:*:*:*:*"},{"name":"syft:cpe23","value":"cpe:2.3:a:jdom:adapters:1.0:*:*:*:*:*:*:*"},{"name":"syft:cpe23","value":"cpe:2.3:a:jdom_org:jdom:1.0:*:*:*:*:*:*:*"},{"name":"syft:cpe23","value":"cpe:2.3:a:org.jdom:jdom:1.0:*:*:*:*:*:*:*"},{"name":"syft:cpe23","value":"cpe:2.3:a:output:filter:1.0:*:*:*:*:*:*:*"},{"name":"syft:cpe23","value":"cpe:2.3:a:output:output:1.0:*:*:*:*:*:*:*"},{"name":"syft:cpe23","value":"cpe:2.3:a:filter:input:1.0:*:*:*:*:*:*:*"},{"name":"syft:cpe23","value":"cpe:2.3:a:filter:xpath:1.0:*:*:*:*:*:*:*"},{"name":"syft:cpe23","value":"cpe:2.3:a:input:filter:1.0:*:*:*:*:*:*:*"},{"name":"syft:cpe23","value":"cpe:2.3:a:input:output:1.0:*:*:*:*:*:*:*"},{"name":"syft:cpe23","value":"cpe:2.3:a:output:input:1.0:*:*:*:*:*:*:*"},{"name":"syft:cpe23","value":"cpe:2.3:a:output:xpath:1.0:*:*:*:*:*:*:*"},{"name":"syft:cpe23","value":"cpe:2.3:a:xpath:filter:1.0:*:*:*:*:*:*:*"},{"name":"syft:cpe23","value":"cpe:2.3:a:xpath:output:1.0:*:*:*:*:*:*:*"},{"name":"syft:cpe23","value":"cpe:2.3:a:filter:jdom:1.0:*:*:*:*:*:*:*"},{"name":"syft:cpe23","value":"cpe:2.3:a:input:input:1.0:*:*:*:*:*:*:*"},{"name":"syft:cpe23","value":"cpe:2.3:a:input:xpath:1.0:*:*:*:*:*:*:*"},{"name":"syft:cpe23","value":"cpe:2.3:a:jdom:filter:1.0:*:*:*:*:*:*:*"},{"name":"syft:cpe23","value":"cpe:2.3:a:jdom:output:1.0:*:*:*:*:*:*:*"},{"name":"syft:cpe23","value":"cpe:2.3:a:output:jdom:1.0:*:*:*:*:*:*:*"},{"name":"syft:cpe23","value":"cpe:2.3:a:xpath:input:1.0:*:*:*:*:*:*:*"},{"name":"syft:cpe23","value":"cpe:2.3:a:xpath:xpath:1.0:*:*:*:*:*:*:*"},{"name":"syft:cpe23","value":"cpe:2.3:a:input:jdom:1.0:*:*:*:*:*:*:*"},{"name":"syft:cpe23","value":"cpe:2.3:a:jdom:input:1.0:*:*:*:*:*:*:*"},{"name":"syft:cpe23","value":"cpe:2.3:a:jdom:xpath:1.0:*:*:*:*:*:*:*"},{"name":"syft:cpe23","value":"cpe:2.3:a:xpath:jdom:1.0:*:*:*:*:*:*:*"},{"name":"syft:cpe23","value":"cpe:2.3:a:jdom:jdom:1.0:*:*:*:*:*:*:*"},{"name":"syft:location:0:path","value":"\\example\\cargo\\lib\\jdom.jar"},{"name":"syft:metadata:virtualPath","value":"\\example\\cargo\\lib\\jdom.jar"}]},{"bom-ref":"pkg:maven/org.jdon/jdon-hibernate3x@6.6.4?package-id=4c4284c062d55234","type":"library","name":"jdon-hibernate3x","version":"6.6.4","cpe":"cpe:2.3:a:jdon-hibernate3x:jdon-hibernate3x:6.6.4:*:*:*:*:*:*:*","purl":"pkg:maven/org.jdon/jdon-hibernate3x@6.6.4","properties":[{"name":"syft:package:foundBy","value":"java-pom-cataloger"},{"name":"syft:package:language","value":"java"},{"name":"syft:package:type","value":"java-archive"},{"name":"syft:package:metadataType","value":"java-archive"},{"name":"syft:cpe23","value":"cpe:2.3:a:jdon-hibernate3x:jdon_hibernate3x:6.6.4:*:*:*:*:*:*:*"},{"name":"syft:cpe23","value":"cpe:2.3:a:jdon_hibernate3x:jdon-hibernate3x:6.6.4:*:*:*:*:*:*:*"},{"name":"syft:cpe23","value":"cpe:2.3:a:jdon_hibernate3x:jdon_hibernate3x:6.6.4:*:*:*:*:*:*:*"},{"name":"syft:cpe23","value":"cpe:2.3:a:org.sonatype.oss:jdon-hibernate3x:6.6.4:*:*:*:*:*:*:*"},{"name":"syft:cpe23","value":"cpe:2.3:a:org.sonatype.oss:jdon_hibernate3x:6.6.4:*:*:*:*:*:*:*"},{"name":"syft:cpe23","value":"cpe:2.3:a:org.jdon:jdon-hibernate3x:6.6.4:*:*:*:*:*:*:*"},{"name":"syft:cpe23","value":"cpe:2.3:a:org.jdon:jdon_hibernate3x:6.6.4:*:*:*:*:*:*:*"},{"name":"syft:cpe23","value":"cpe:2.3:a:sonatype:jdon-hibernate3x:6.6.4:*:*:*:*:*:*:*"},{"name":"syft:cpe23","value":"cpe:2.3:a:sonatype:jdon_hibernate3x:6.6.4:*:*:*:*:*:*:*"},{"name":"syft:cpe23","value":"cpe:2.3:a:jdon:jdon-hibernate3x:6.6.4:*:*:*:*:*:*:*"},{"name":"syft:cpe23","value":"cpe:2.3:a:jdon:jdon_hibernate3x:6.6.4:*:*:*:*:*:*:*"},{"name":"syft:cpe23","value":"cpe:2.3:a:jdon-hibernate3x:oss:6.6.4:*:*:*:*:*:*:*"},{"name":"syft:cpe23","value":"cpe:2.3:a:jdon_hibernate3x:oss:6.6.4:*:*:*:*:*:*:*"},{"name":"syft:cpe23","value":"cpe:2.3:a:org.sonatype.oss:oss:6.6.4:*:*:*:*:*:*:*"},{"name":"syft:cpe23","value":"cpe:2.3:a:oss:jdon-hibernate3x:6.6.4:*:*:*:*:*:*:*"},{"name":"syft:cpe23","value":"cpe:2.3:a:oss:jdon_hibernate3x:6.6.4:*:*:*:*:*:*:*"},{"name":"syft:cpe23","value":"cpe:2.3:a:org.jdon:oss:6.6.4:*:*:*:*:*:*:*"},{"name":"syft:cpe23","value":"cpe:2.3:a:sonatype:oss:6.6.4:*:*:*:*:*:*:*"},{"name":"syft:cpe23","value":"cpe:2.3:a:jdon:oss:6.6.4:*:*:*:*:*:*:*"},{"name":"syft:cpe23","value":"cpe:2.3:a:oss:oss:6.6.4:*:*:*:*:*:*:*"},{"name":"syft:location:0:path","value":"\\JdonAccessory\\jdon-hibernate3x\\pom.xml"}]},{"bom-ref":"pkg:maven/org.jdon/jdon-jdbc@6.6.4?package-id=63095f4021d871b6","type":"library","name":"jdon-jdbc","version":"6.6.4","cpe":"cpe:2.3:a:org.sonatype.oss:jdon-jdbc:6.6.4:*:*:*:*:*:*:*","purl":"pkg:maven/org.jdon/jdon-jdbc@6.6.4","properties":[{"name":"syft:package:foundBy","value":"java-pom-cataloger"},{"name":"syft:package:language","value":"java"},{"name":"syft:package:type","value":"java-archive"},{"name":"syft:package:metadataType","value":"java-archive"},{"name":"syft:cpe23","value":"cpe:2.3:a:org.sonatype.oss:jdon_jdbc:6.6.4:*:*:*:*:*:*:*"},{"name":"syft:cpe23","value":"cpe:2.3:a:org.sonatype.oss:oss:6.6.4:*:*:*:*:*:*:*"},{"name":"syft:cpe23","value":"cpe:2.3:a:jdon-jdbc:jdon-jdbc:6.6.4:*:*:*:*:*:*:*"},{"name":"syft:cpe23","value":"cpe:2.3:a:jdon-jdbc:jdon_jdbc:6.6.4:*:*:*:*:*:*:*"},{"name":"syft:cpe23","value":"cpe:2.3:a:jdon_jdbc:jdon-jdbc:6.6.4:*:*:*:*:*:*:*"},{"name":"syft:cpe23","value":"cpe:2.3:a:jdon_jdbc:jdon_jdbc:6.6.4:*:*:*:*:*:*:*"},{"name":"syft:cpe23","value":"cpe:2.3:a:org.jdon:jdon-jdbc:6.6.4:*:*:*:*:*:*:*"},{"name":"syft:cpe23","value":"cpe:2.3:a:org.jdon:jdon_jdbc:6.6.4:*:*:*:*:*:*:*"},{"name":"syft:cpe23","value":"cpe:2.3:a:sonatype:jdon-jdbc:6.6.4:*:*:*:*:*:*:*"},{"name":"syft:cpe23","value":"cpe:2.3:a:sonatype:jdon_jdbc:6.6.4:*:*:*:*:*:*:*"},{"name":"syft:cpe23","value":"cpe:2.3:a:jdon:jdon-jdbc:6.6.4:*:*:*:*:*:*:*"},{"name":"syft:cpe23","value":"cpe:2.3:a:jdon:jdon_jdbc:6.6.4:*:*:*:*:*:*:*"},{"name":"syft:cpe23","value":"cpe:2.3:a:jdon-jdbc:oss:6.6.4:*:*:*:*:*:*:*"},{"name":"syft:cpe23","value":"cpe:2.3:a:jdon_jdbc:oss:6.6.4:*:*:*:*:*:*:*"},{"name":"syft:cpe23","value":"cpe:2.3:a:oss:jdon-jdbc:6.6.4:*:*:*:*:*:*:*"},{"name":"syft:cpe23","value":"cpe:2.3:a:oss:jdon_jdbc:6.6.4:*:*:*:*:*:*:*"},{"name":"syft:cpe23","value":"cpe:2.3:a:org.jdon:oss:6.6.4:*:*:*:*:*:*:*"},{"name":"syft:cpe23","value":"cpe:2.3:a:sonatype:oss:6.6.4:*:*:*:*:*:*:*"},{"name":"syft:cpe23","value":"cpe:2.3:a:jdon:oss:6.6.4:*:*:*:*:*:*:*"},{"name":"syft:cpe23","value":"cpe:2.3:a:oss:oss:6.6.4:*:*:*:*:*:*:*"},{"name":"syft:location:0:path","value":"\\JdonAccessory\\jdon-jdbc\\pom.xml"}]},{"bom-ref":"pkg:maven/com.jdon/jdon-jdbc@6.6.4?package-id=7de7fb3b5d85abe0","type":"library","group":"com.jdon","name":"jdon-jdbc","version":"6.6.4","cpe":"cpe:2.3:a:jdon-jdbc:jdon-jdbc:6.6.4:*:*:*:*:*:*:*","purl":"pkg:maven/com.jdon/jdon-jdbc@6.6.4","properties":[{"name":"syft:package:foundBy","value":"java-pom-cataloger"},{"name":"syft:package:language","value":"java"},{"name":"syft:package:type","value":"java-archive"},{"name":"syft:package:metadataType","value":"java-archive"},{"name":"syft:cpe23","value":"cpe:2.3:a:jdon-jdbc:jdon_jdbc:6.6.4:*:*:*:*:*:*:*"},{"name":"syft:cpe23","value":"cpe:2.3:a:jdon_jdbc:jdon-jdbc:6.6.4:*:*:*:*:*:*:*"},{"name":"syft:cpe23","value":"cpe:2.3:a:jdon_jdbc:jdon_jdbc:6.6.4:*:*:*:*:*:*:*"},{"name":"syft:cpe23","value":"cpe:2.3:a:com.jdon:jdon-jdbc:6.6.4:*:*:*:*:*:*:*"},{"name":"syft:cpe23","value":"cpe:2.3:a:com.jdon:jdon_jdbc:6.6.4:*:*:*:*:*:*:*"},{"name":"syft:cpe23","value":"cpe:2.3:a:jdon:jdon-jdbc:6.6.4:*:*:*:*:*:*:*"},{"name":"syft:cpe23","value":"cpe:2.3:a:jdon:jdon_jdbc:6.6.4:*:*:*:*:*:*:*"},{"name":"syft:location:0:path","value":"\\doc\\english\\pom.xml"},{"name":"syft:metadata:-:artifactID","value":"jdon-jdbc"},{"name":"syft:metadata:-:groupID","value":"com.jdon"}]},{"bom-ref":"pkg:maven/org.jdon/jdon-remote@6.6.4?package-id=886c57dc392f2309","type":"library","name":"jdon-remote","version":"6.6.4","cpe":"cpe:2.3:a:org.sonatype.oss:jdon-remote:6.6.4:*:*:*:*:*:*:*","purl":"pkg:maven/org.jdon/jdon-remote@6.6.4","properties":[{"name":"syft:package:foundBy","value":"java-pom-cataloger"},{"name":"syft:package:language","value":"java"},{"name":"syft:package:type","value":"java-archive"},{"name":"syft:package:metadataType","value":"java-archive"},{"name":"syft:cpe23","value":"cpe:2.3:a:org.sonatype.oss:jdon_remote:6.6.4:*:*:*:*:*:*:*"},{"name":"syft:cpe23","value":"cpe:2.3:a:jdon-remote:jdon-remote:6.6.4:*:*:*:*:*:*:*"},{"name":"syft:cpe23","value":"cpe:2.3:a:jdon-remote:jdon_remote:6.6.4:*:*:*:*:*:*:*"},{"name":"syft:cpe23","value":"cpe:2.3:a:jdon_remote:jdon-remote:6.6.4:*:*:*:*:*:*:*"},{"name":"syft:cpe23","value":"cpe:2.3:a:jdon_remote:jdon_remote:6.6.4:*:*:*:*:*:*:*"},{"name":"syft:cpe23","value":"cpe:2.3:a:org.jdon:jdon-remote:6.6.4:*:*:*:*:*:*:*"},{"name":"syft:cpe23","value":"cpe:2.3:a:org.jdon:jdon_remote:6.6.4:*:*:*:*:*:*:*"},{"name":"syft:cpe23","value":"cpe:2.3:a:org.sonatype.oss:oss:6.6.4:*:*:*:*:*:*:*"},{"name":"syft:cpe23","value":"cpe:2.3:a:sonatype:jdon-remote:6.6.4:*:*:*:*:*:*:*"},{"name":"syft:cpe23","value":"cpe:2.3:a:sonatype:jdon_remote:6.6.4:*:*:*:*:*:*:*"},{"name":"syft:cpe23","value":"cpe:2.3:a:jdon:jdon-remote:6.6.4:*:*:*:*:*:*:*"},{"name":"syft:cpe23","value":"cpe:2.3:a:jdon:jdon_remote:6.6.4:*:*:*:*:*:*:*"},{"name":"syft:cpe23","value":"cpe:2.3:a:jdon-remote:oss:6.6.4:*:*:*:*:*:*:*"},{"name":"syft:cpe23","value":"cpe:2.3:a:jdon_remote:oss:6.6.4:*:*:*:*:*:*:*"},{"name":"syft:cpe23","value":"cpe:2.3:a:oss:jdon-remote:6.6.4:*:*:*:*:*:*:*"},{"name":"syft:cpe23","value":"cpe:2.3:a:oss:jdon_remote:6.6.4:*:*:*:*:*:*:*"},{"name":"syft:cpe23","value":"cpe:2.3:a:org.jdon:oss:6.6.4:*:*:*:*:*:*:*"},{"name":"syft:cpe23","value":"cpe:2.3:a:sonatype:oss:6.6.4:*:*:*:*:*:*:*"},{"name":"syft:cpe23","value":"cpe:2.3:a:jdon:oss:6.6.4:*:*:*:*:*:*:*"},{"name":"syft:cpe23","value":"cpe:2.3:a:oss:oss:6.6.4:*:*:*:*:*:*:*"},{"name":"syft:location:0:path","value":"\\JdonAccessory\\jdon-remote\\pom.xml"}]},{"bom-ref":"pkg:maven/org.jdon/jdon-struts1x@6.6.4?package-id=a77f1b6e0337129e","type":"library","name":"jdon-struts1x","version":"6.6.4","cpe":"cpe:2.3:a:org.sonatype.oss:jdon-struts1x:6.6.4:*:*:*:*:*:*:*","purl":"pkg:maven/org.jdon/jdon-struts1x@6.6.4","properties":[{"name":"syft:package:foundBy","value":"java-pom-cataloger"},{"name":"syft:package:language","value":"java"},{"name":"syft:package:type","value":"java-archive"},{"name":"syft:package:metadataType","value":"java-archive"},{"name":"syft:cpe23","value":"cpe:2.3:a:org.sonatype.oss:jdon_struts1x:6.6.4:*:*:*:*:*:*:*"},{"name":"syft:cpe23","value":"cpe:2.3:a:jdon-struts1x:jdon-struts1x:6.6.4:*:*:*:*:*:*:*"},{"name":"syft:cpe23","value":"cpe:2.3:a:jdon-struts1x:jdon_struts1x:6.6.4:*:*:*:*:*:*:*"},{"name":"syft:cpe23","value":"cpe:2.3:a:jdon_struts1x:jdon-struts1x:6.6.4:*:*:*:*:*:*:*"},{"name":"syft:cpe23","value":"cpe:2.3:a:jdon_struts1x:jdon_struts1x:6.6.4:*:*:*:*:*:*:*"},{"name":"syft:cpe23","value":"cpe:2.3:a:org.jdon:jdon-struts1x:6.6.4:*:*:*:*:*:*:*"},{"name":"syft:cpe23","value":"cpe:2.3:a:org.jdon:jdon_struts1x:6.6.4:*:*:*:*:*:*:*"},{"name":"syft:cpe23","value":"cpe:2.3:a:sonatype:jdon-struts1x:6.6.4:*:*:*:*:*:*:*"},{"name":"syft:cpe23","value":"cpe:2.3:a:sonatype:jdon_struts1x:6.6.4:*:*:*:*:*:*:*"},{"name":"syft:cpe23","value":"cpe:2.3:a:org.sonatype.oss:oss:6.6.4:*:*:*:*:*:*:*"},{"name":"syft:cpe23","value":"cpe:2.3:a:jdon:jdon-struts1x:6.6.4:*:*:*:*:*:*:*"},{"name":"syft:cpe23","value":"cpe:2.3:a:jdon:jdon_struts1x:6.6.4:*:*:*:*:*:*:*"},{"name":"syft:cpe23","value":"cpe:2.3:a:jdon-struts1x:oss:6.6.4:*:*:*:*:*:*:*"},{"name":"syft:cpe23","value":"cpe:2.3:a:jdon_struts1x:oss:6.6.4:*:*:*:*:*:*:*"},{"name":"syft:cpe23","value":"cpe:2.3:a:oss:jdon-struts1x:6.6.4:*:*:*:*:*:*:*"},{"name":"syft:cpe23","value":"cpe:2.3:a:oss:jdon_struts1x:6.6.4:*:*:*:*:*:*:*"},{"name":"syft:cpe23","value":"cpe:2.3:a:org.jdon:oss:6.6.4:*:*:*:*:*:*:*"},{"name":"syft:cpe23","value":"cpe:2.3:a:sonatype:oss:6.6.4:*:*:*:*:*:*:*"},{"name":"syft:cpe23","value":"cpe:2.3:a:jdon:oss:6.6.4:*:*:*:*:*:*:*"},{"name":"syft:cpe23","value":"cpe:2.3:a:oss:oss:6.6.4:*:*:*:*:*:*:*"},{"name":"syft:location:0:path","value":"\\JdonAccessory\\jdon-struts1x\\pom.xml"}]},{"bom-ref":"pkg:maven/com.jdon/jdon-struts1x@6.6.4?package-id=dd500831ccd70f85","type":"library","group":"com.jdon","name":"jdon-struts1x","version":"6.6.4","cpe":"cpe:2.3:a:jdon-struts1x:jdon-struts1x:6.6.4:*:*:*:*:*:*:*","purl":"pkg:maven/com.jdon/jdon-struts1x@6.6.4","properties":[{"name":"syft:package:foundBy","value":"java-pom-cataloger"},{"name":"syft:package:language","value":"java"},{"name":"syft:package:type","value":"java-archive"},{"name":"syft:package:metadataType","value":"java-archive"},{"name":"syft:cpe23","value":"cpe:2.3:a:jdon-struts1x:jdon_struts1x:6.6.4:*:*:*:*:*:*:*"},{"name":"syft:cpe23","value":"cpe:2.3:a:jdon_struts1x:jdon-struts1x:6.6.4:*:*:*:*:*:*:*"},{"name":"syft:cpe23","value":"cpe:2.3:a:jdon_struts1x:jdon_struts1x:6.6.4:*:*:*:*:*:*:*"},{"name":"syft:cpe23","value":"cpe:2.3:a:com.jdon:jdon-struts1x:6.6.4:*:*:*:*:*:*:*"},{"name":"syft:cpe23","value":"cpe:2.3:a:com.jdon:jdon_struts1x:6.6.4:*:*:*:*:*:*:*"},{"name":"syft:cpe23","value":"cpe:2.3:a:jdon:jdon-struts1x:6.6.4:*:*:*:*:*:*:*"},{"name":"syft:cpe23","value":"cpe:2.3:a:jdon:jdon_struts1x:6.6.4:*:*:*:*:*:*:*"},{"name":"syft:location:0:path","value":"\\doc\\english\\pom.xml"},{"name":"syft:metadata:-:artifactID","value":"jdon-struts1x"},{"name":"syft:metadata:-:groupID","value":"com.jdon"}]},{"bom-ref":"pkg:maven/jdonFramework/jdonFramework?package-id=c3a26558880deb68","type":"library","name":"jdonFramework","version":"UNKNOWN","cpe":"cpe:2.3:a:jdonFramework:jdonFramework:*:*:*:*:*:*:*:*","purl":"pkg:maven/jdonFramework/jdonFramework","externalReferences":[{"url":"","hashes":[{"alg":"SHA-1","content":"fefcf1b6a8b725f24d1058aa73b5a5131a62394e"}],"type":"build-meta"}],"properties":[{"name":"syft:package:foundBy","value":"java-archive-cataloger"},{"name":"syft:package:language","value":"java"},{"name":"syft:package:type","value":"java-archive"},{"name":"syft:package:metadataType","value":"java-archive"},{"name":"syft:location:0:path","value":"\\example\\cargo\\lib\\jdonFramework.jar"},{"name":"syft:metadata:virtualPath","value":"\\example\\cargo\\lib\\jdonFramework.jar"}]},{"bom-ref":"pkg:maven/com.jdon/jdonJ2EE@6.6.4?package-id=d5403c1753bd80d4","type":"library","group":"com.jdon","name":"jdonJ2EE","version":"6.6.4","cpe":"cpe:2.3:a:com.jdon:jdonJ2EE:6.6.4:*:*:*:*:*:*:*","purl":"pkg:maven/com.jdon/jdonJ2EE@6.6.4","properties":[{"name":"syft:package:foundBy","value":"java-pom-cataloger"},{"name":"syft:package:language","value":"java"},{"name":"syft:package:type","value":"java-archive"},{"name":"syft:package:metadataType","value":"java-archive"},{"name":"syft:cpe23","value":"cpe:2.3:a:jdonJ2EE:jdonJ2EE:6.6.4:*:*:*:*:*:*:*"},{"name":"syft:cpe23","value":"cpe:2.3:a:jdon:jdonJ2EE:6.6.4:*:*:*:*:*:*:*"},{"name":"syft:location:0:path","value":"\\JdonAccessory\\jdon-hibernate3x\\pom.xml"},{"name":"syft:metadata:-:artifactID","value":"jdonJ2EE"},{"name":"syft:metadata:-:groupID","value":"com.jdon"}]},{"bom-ref":"pkg:maven/org.jdon/jdonframework@6.6.4?package-id=762643f6c5e12007","type":"library","group":"org.jdon","name":"jdonframework","version":"6.6.4","cpe":"cpe:2.3:a:jdonframework:jdonframework:6.6.4:*:*:*:*:*:*:*","purl":"pkg:maven/org.jdon/jdonframework@6.6.4","properties":[{"name":"syft:package:foundBy","value":"java-pom-cataloger"},{"name":"syft:package:language","value":"java"},{"name":"syft:package:type","value":"java-archive"},{"name":"syft:package:metadataType","value":"java-archive"},{"name":"syft:cpe23","value":"cpe:2.3:a:org.jdon:jdonframework:6.6.4:*:*:*:*:*:*:*"},{"name":"syft:cpe23","value":"cpe:2.3:a:jdon:jdonframework:6.6.4:*:*:*:*:*:*:*"},{"name":"syft:location:0:path","value":"\\JdonAccessory\\jdon-hibernate3x\\pom.xml"},{"name":"syft:metadata:-:artifactID","value":"jdonframework"},{"name":"syft:metadata:-:groupID","value":"org.jdon"}]},{"bom-ref":"pkg:maven/org.jdon/jdonframework@6.9?package-id=59c90396b7e2c2fa","type":"library","name":"jdonframework","version":"6.9","licenses":[{"license":{"name":"The Apache Software License, Version 2.0","url":"http://www.apache.org/licenses/LICENSE-2.0.txt"}}],"cpe":"cpe:2.3:a:jdonframework:jdonframework:6.9:*:*:*:*:*:*:*","purl":"pkg:maven/org.jdon/jdonframework@6.9","properties":[{"name":"syft:package:foundBy","value":"java-pom-cataloger"},{"name":"syft:package:language","value":"java"},{"name":"syft:package:type","value":"java-archive"},{"name":"syft:package:metadataType","value":"java-archive"},{"name":"syft:cpe23","value":"cpe:2.3:a:org.jdon:jdonframework:6.9:*:*:*:*:*:*:*"},{"name":"syft:cpe23","value":"cpe:2.3:a:jdon:jdonframework:6.9:*:*:*:*:*:*:*"},{"name":"syft:location:0:path","value":"\\pom.xml"}]},{"bom-ref":"pkg:maven/com.jdon.mvc/jdonmvc-core@1.0-SNAPSHOT?package-id=11f08e6a0173854a","type":"library","group":"com.jdon.mvc","name":"jdonmvc-core","version":"1.0-SNAPSHOT","cpe":"cpe:2.3:a:com.jdon.mvc:jdonmvc-core:1.0-SNAPSHOT:*:*:*:*:*:*:*","purl":"pkg:maven/com.jdon.mvc/jdonmvc-core@1.0-SNAPSHOT","properties":[{"name":"syft:package:foundBy","value":"java-pom-cataloger"},{"name":"syft:package:language","value":"java"},{"name":"syft:package:type","value":"java-archive"},{"name":"syft:package:metadataType","value":"java-archive"},{"name":"syft:cpe23","value":"cpe:2.3:a:com.jdon.mvc:jdonmvc_core:1.0-SNAPSHOT:*:*:*:*:*:*:*"},{"name":"syft:cpe23","value":"cpe:2.3:a:jdonmvc-core:jdonmvc-core:1.0-SNAPSHOT:*:*:*:*:*:*:*"},{"name":"syft:cpe23","value":"cpe:2.3:a:jdonmvc-core:jdonmvc_core:1.0-SNAPSHOT:*:*:*:*:*:*:*"},{"name":"syft:cpe23","value":"cpe:2.3:a:jdonmvc_core:jdonmvc-core:1.0-SNAPSHOT:*:*:*:*:*:*:*"},{"name":"syft:cpe23","value":"cpe:2.3:a:jdonmvc_core:jdonmvc_core:1.0-SNAPSHOT:*:*:*:*:*:*:*"},{"name":"syft:cpe23","value":"cpe:2.3:a:jdonmvc:jdonmvc-core:1.0-SNAPSHOT:*:*:*:*:*:*:*"},{"name":"syft:cpe23","value":"cpe:2.3:a:jdonmvc:jdonmvc_core:1.0-SNAPSHOT:*:*:*:*:*:*:*"},{"name":"syft:cpe23","value":"cpe:2.3:a:jdon:jdonmvc-core:1.0-SNAPSHOT:*:*:*:*:*:*:*"},{"name":"syft:cpe23","value":"cpe:2.3:a:jdon:jdonmvc_core:1.0-SNAPSHOT:*:*:*:*:*:*:*"},{"name":"syft:cpe23","value":"cpe:2.3:a:mvc:jdonmvc-core:1.0-SNAPSHOT:*:*:*:*:*:*:*"},{"name":"syft:cpe23","value":"cpe:2.3:a:mvc:jdonmvc_core:1.0-SNAPSHOT:*:*:*:*:*:*:*"},{"name":"syft:location:0:path","value":"\\example\\jdonMVC+CQRS+ES\\pom.xml"},{"name":"syft:metadata:-:artifactID","value":"jdonmvc-core"},{"name":"syft:metadata:-:groupID","value":"com.jdon.mvc"}]},{"bom-ref":"pkg:maven/com.jdon/jdonmvc_cqrs_es@1.0?package-id=e0a2954c8ee06bc9","type":"library","name":"jdonmvc_cqrs_es","version":"1.0","cpe":"cpe:2.3:a:jdonmvc-cqrs-es:jdonmvc-cqrs-es:1.0:*:*:*:*:*:*:*","purl":"pkg:maven/com.jdon/jdonmvc_cqrs_es@1.0","properties":[{"name":"syft:package:foundBy","value":"java-pom-cataloger"},{"name":"syft:package:language","value":"java"},{"name":"syft:package:type","value":"java-archive"},{"name":"syft:package:metadataType","value":"java-archive"},{"name":"syft:cpe23","value":"cpe:2.3:a:jdonmvc-cqrs-es:jdonmvc_cqrs_es:1.0:*:*:*:*:*:*:*"},{"name":"syft:cpe23","value":"cpe:2.3:a:jdonmvc_cqrs_es:jdonmvc-cqrs-es:1.0:*:*:*:*:*:*:*"},{"name":"syft:cpe23","value":"cpe:2.3:a:jdonmvc_cqrs_es:jdonmvc_cqrs_es:1.0:*:*:*:*:*:*:*"},{"name":"syft:cpe23","value":"cpe:2.3:a:jdonmvc-cqrs:jdonmvc-cqrs-es:1.0:*:*:*:*:*:*:*"},{"name":"syft:cpe23","value":"cpe:2.3:a:jdonmvc-cqrs:jdonmvc_cqrs_es:1.0:*:*:*:*:*:*:*"},{"name":"syft:cpe23","value":"cpe:2.3:a:jdonmvc_cqrs:jdonmvc-cqrs-es:1.0:*:*:*:*:*:*:*"},{"name":"syft:cpe23","value":"cpe:2.3:a:jdonmvc_cqrs:jdonmvc_cqrs_es:1.0:*:*:*:*:*:*:*"},{"name":"syft:cpe23","value":"cpe:2.3:a:com.jdon:jdonmvc-cqrs-es:1.0:*:*:*:*:*:*:*"},{"name":"syft:cpe23","value":"cpe:2.3:a:com.jdon:jdonmvc_cqrs_es:1.0:*:*:*:*:*:*:*"},{"name":"syft:cpe23","value":"cpe:2.3:a:jdonmvc:jdonmvc-cqrs-es:1.0:*:*:*:*:*:*:*"},{"name":"syft:cpe23","value":"cpe:2.3:a:jdonmvc:jdonmvc_cqrs_es:1.0:*:*:*:*:*:*:*"},{"name":"syft:cpe23","value":"cpe:2.3:a:jdon:jdonmvc-cqrs-es:1.0:*:*:*:*:*:*:*"},{"name":"syft:cpe23","value":"cpe:2.3:a:jdon:jdonmvc_cqrs_es:1.0:*:*:*:*:*:*:*"},{"name":"syft:location:0:path","value":"\\example\\jdonMVC+CQRS+ES\\pom.xml"}]},{"bom-ref":"pkg:maven/org.apache.tomcat/jsp-api@6.0.37?package-id=474468ca88938657","type":"library","group":"org.apache.tomcat","name":"jsp-api","version":"6.0.37","cpe":"cpe:2.3:a:apache:jsp-api:6.0.37:*:*:*:*:*:*:*","purl":"pkg:maven/org.apache.tomcat/jsp-api@6.0.37","properties":[{"name":"syft:package:foundBy","value":"java-pom-cataloger"},{"name":"syft:package:language","value":"java"},{"name":"syft:package:type","value":"java-archive"},{"name":"syft:package:metadataType","value":"java-archive"},{"name":"syft:cpe23","value":"cpe:2.3:a:apache:jsp_api:6.0.37:*:*:*:*:*:*:*"},{"name":"syft:location:0:path","value":"\\JdonAccessory\\jdon-hibernate3x\\pom.xml"},{"name":"syft:metadata:-:artifactID","value":"jsp-api"},{"name":"syft:metadata:-:groupID","value":"org.apache.tomcat"}]},{"bom-ref":"pkg:maven/javax.ws.rs/jsr311-api@1.1.1?package-id=8f6ea7a852c8f205","type":"library","group":"javax.ws.rs","name":"jsr311-api","version":"1.1.1","cpe":"cpe:2.3:a:jsr311-api:jsr311-api:1.1.1:*:*:*:*:*:*:*","purl":"pkg:maven/javax.ws.rs/jsr311-api@1.1.1","properties":[{"name":"syft:package:foundBy","value":"java-pom-cataloger"},{"name":"syft:package:language","value":"java"},{"name":"syft:package:type","value":"java-archive"},{"name":"syft:package:metadataType","value":"java-archive"},{"name":"syft:cpe23","value":"cpe:2.3:a:jsr311-api:jsr311_api:1.1.1:*:*:*:*:*:*:*"},{"name":"syft:cpe23","value":"cpe:2.3:a:jsr311_api:jsr311-api:1.1.1:*:*:*:*:*:*:*"},{"name":"syft:cpe23","value":"cpe:2.3:a:jsr311_api:jsr311_api:1.1.1:*:*:*:*:*:*:*"},{"name":"syft:cpe23","value":"cpe:2.3:a:jsr311:jsr311-api:1.1.1:*:*:*:*:*:*:*"},{"name":"syft:cpe23","value":"cpe:2.3:a:jsr311:jsr311_api:1.1.1:*:*:*:*:*:*:*"},{"name":"syft:location:0:path","value":"\\example\\jdonMVC+CQRS+ES\\pom.xml"},{"name":"syft:metadata:-:artifactID","value":"jsr311-api"},{"name":"syft:metadata:-:groupID","value":"javax.ws.rs"}]},{"bom-ref":"pkg:maven/jstl/jstl@1.2?package-id=23bfee3a2711adc7","type":"library","group":"jstl","name":"jstl","version":"1.2","cpe":"cpe:2.3:a:jstl:jstl:1.2:*:*:*:*:*:*:*","purl":"pkg:maven/jstl/jstl@1.2","properties":[{"name":"syft:package:foundBy","value":"java-pom-cataloger"},{"name":"syft:package:language","value":"java"},{"name":"syft:package:type","value":"java-archive"},{"name":"syft:package:metadataType","value":"java-archive"},{"name":"syft:location:0:path","value":"\\example\\jdonMVC+CQRS+ES\\pom.xml"},{"name":"syft:metadata:-:artifactID","value":"jstl"},{"name":"syft:metadata:-:groupID","value":"jstl"}]},{"bom-ref":"pkg:maven/junit/junit@3.8.1?package-id=e2199aa12519ad9a","type":"library","group":"junit","name":"junit","version":"3.8.1","cpe":"cpe:2.3:a:junit:junit:3.8.1:*:*:*:*:*:*:*","purl":"pkg:maven/junit/junit@3.8.1","properties":[{"name":"syft:package:foundBy","value":"java-pom-cataloger"},{"name":"syft:package:language","value":"java"},{"name":"syft:package:type","value":"java-archive"},{"name":"syft:package:metadataType","value":"java-archive"},{"name":"syft:location:0:path","value":"\\JdonAccessory\\jdon-hibernate3x\\pom.xml"},{"name":"syft:metadata:-:artifactID","value":"junit"},{"name":"syft:metadata:-:groupID","value":"junit"}]},{"bom-ref":"pkg:maven/junit/junit?package-id=e1f6237351c953a9","type":"library","name":"junit","version":"UNKNOWN","cpe":"cpe:2.3:a:junit:junit:*:*:*:*:*:*:*:*","purl":"pkg:maven/junit/junit","externalReferences":[{"url":"","hashes":[{"alg":"SHA-1","content":"ff0882b42fc5857df39e5acdb30c38ba6a9a505c"}],"type":"build-meta"}],"properties":[{"name":"syft:package:foundBy","value":"java-archive-cataloger"},{"name":"syft:package:language","value":"java"},{"name":"syft:package:type","value":"java-archive"},{"name":"syft:package:metadataType","value":"java-archive"},{"name":"syft:location:0:path","value":"\\example\\cargo\\lib\\junit.jar"},{"name":"syft:metadata:virtualPath","value":"\\example\\cargo\\lib\\junit.jar"}]},{"bom-ref":"pkg:maven/log4j/log4j@1.2.15?package-id=0ee37bb9285fddaa","type":"library","group":"log4j","name":"log4j","version":"1.2.15","licenses":[{"license":{"id":"Apache-2.0"}}],"cpe":"cpe:2.3:a:apache:log4j:1.2.15:*:*:*:*:*:*:*","purl":"pkg:maven/log4j/log4j@1.2.15","externalReferences":[{"url":"","hashes":[{"alg":"SHA-1","content":"f0a0d2e29ed910808c33135a3a5a51bba6358f7b"}],"type":"build-meta"}],"properties":[{"name":"syft:package:foundBy","value":"java-archive-cataloger"},{"name":"syft:package:language","value":"java"},{"name":"syft:package:type","value":"java-archive"},{"name":"syft:package:metadataType","value":"java-archive"},{"name":"syft:location:0:path","value":"\\example\\cargo\\lib\\log4j.jar"},{"name":"syft:metadata:-:artifactID","value":"log4j"},{"name":"syft:metadata:-:groupID","value":"log4j"},{"name":"syft:metadata:virtualPath","value":"\\example\\cargo\\lib\\log4j.jar"}]},{"bom-ref":"pkg:maven/log4j/log4j@1.2.4?package-id=78c5c2f8c68c35f2","type":"library","group":"log4j","name":"log4j","version":"1.2.4","cpe":"cpe:2.3:a:apache:log4j:1.2.4:*:*:*:*:*:*:*","purl":"pkg:maven/log4j/log4j@1.2.4","properties":[{"name":"syft:package:foundBy","value":"java-pom-cataloger"},{"name":"syft:package:language","value":"java"},{"name":"syft:package:type","value":"java-archive"},{"name":"syft:package:metadataType","value":"java-archive"},{"name":"syft:location:0:path","value":"\\doc\\english\\pom.xml"},{"name":"syft:metadata:-:artifactID","value":"log4j"},{"name":"syft:metadata:-:groupID","value":"log4j"}]},{"bom-ref":"pkg:maven/org.apache.logging.log4j/log4j-api@2.11.0?package-id=ab4696285722e9d9","type":"library","group":"org.apache.logging.log4j","name":"log4j-api","version":"2.11.0","cpe":"cpe:2.3:a:apache:log4j-api:2.11.0:*:*:*:*:*:*:*","purl":"pkg:maven/org.apache.logging.log4j/log4j-api@2.11.0","properties":[{"name":"syft:package:foundBy","value":"java-pom-cataloger"},{"name":"syft:package:language","value":"java"},{"name":"syft:package:type","value":"java-archive"},{"name":"syft:package:metadataType","value":"java-archive"},{"name":"syft:cpe23","value":"cpe:2.3:a:apache:log4j_api:2.11.0:*:*:*:*:*:*:*"},{"name":"syft:cpe23","value":"cpe:2.3:a:apache:log4j:2.11.0:*:*:*:*:*:*:*"},{"name":"syft:location:0:path","value":"\\pom.xml"},{"name":"syft:metadata:-:artifactID","value":"log4j-api"},{"name":"syft:metadata:-:groupID","value":"org.apache.logging.log4j"}]},{"bom-ref":"pkg:maven/org.apache.logging.log4j/log4j-core@2.11.0?package-id=6400a51f631fe60c","type":"library","group":"org.apache.logging.log4j","name":"log4j-core","version":"2.11.0","cpe":"cpe:2.3:a:apache:log4j-core:2.11.0:*:*:*:*:*:*:*","purl":"pkg:maven/org.apache.logging.log4j/log4j-core@2.11.0","properties":[{"name":"syft:package:foundBy","value":"java-pom-cataloger"},{"name":"syft:package:language","value":"java"},{"name":"syft:package:type","value":"java-archive"},{"name":"syft:package:metadataType","value":"java-archive"},{"name":"syft:cpe23","value":"cpe:2.3:a:apache:log4j_core:2.11.0:*:*:*:*:*:*:*"},{"name":"syft:cpe23","value":"cpe:2.3:a:apache:log4j:2.11.0:*:*:*:*:*:*:*"},{"name":"syft:location:0:path","value":"\\pom.xml"},{"name":"syft:metadata:-:artifactID","value":"log4j-core"},{"name":"syft:metadata:-:groupID","value":"org.apache.logging.log4j"}]},{"bom-ref":"pkg:maven/org.apache.logging.log4j/log4j2@2.0?package-id=bbfec24abe8645d8","type":"library","group":"org.apache.logging.log4j","name":"log4j2","version":"2.0","cpe":"cpe:2.3:a:apache:log4j2:2.0:*:*:*:*:*:*:*","purl":"pkg:maven/org.apache.logging.log4j/log4j2@2.0","properties":[{"name":"syft:package:foundBy","value":"java-pom-cataloger"},{"name":"syft:package:language","value":"java"},{"name":"syft:package:type","value":"java-archive"},{"name":"syft:package:metadataType","value":"java-archive"},{"name":"syft:cpe23","value":"cpe:2.3:a:apache:log4j:2.0:*:*:*:*:*:*:*"},{"name":"syft:location:0:path","value":"\\JdonAccessory\\jdon-hibernate3x\\pom.xml"},{"name":"syft:metadata:-:artifactID","value":"log4j2"},{"name":"syft:metadata:-:groupID","value":"org.apache.logging.log4j"}]},{"bom-ref":"pkg:maven/sample/match@1.0-SNAPSHOT?package-id=8ac5b599b9c0cdc4","type":"library","name":"match","version":"1.0-SNAPSHOT","cpe":"cpe:2.3:a:match:match:1.0-SNAPSHOT:*:*:*:*:*:*:*","purl":"pkg:maven/sample/match@1.0-SNAPSHOT","properties":[{"name":"syft:package:foundBy","value":"java-pom-cataloger"},{"name":"syft:package:language","value":"java"},{"name":"syft:package:type","value":"java-archive"},{"name":"syft:package:metadataType","value":"java-archive"},{"name":"syft:location:0:path","value":"\\example\\cqrs+es\\match\\pom.xml"}]},{"bom-ref":"pkg:maven/com.thoughtworks.paranamer/paranamer@2.2.1?package-id=e46b1a9ebe34287f","type":"library","group":"com.thoughtworks.paranamer","name":"paranamer","version":"2.2.1","cpe":"cpe:2.3:a:com.thoughtworks.paranamer:paranamer:2.2.1:*:*:*:*:*:*:*","purl":"pkg:maven/com.thoughtworks.paranamer/paranamer@2.2.1","properties":[{"name":"syft:package:foundBy","value":"java-pom-cataloger"},{"name":"syft:package:language","value":"java"},{"name":"syft:package:type","value":"java-archive"},{"name":"syft:package:metadataType","value":"java-archive"},{"name":"syft:cpe23","value":"cpe:2.3:a:thoughtworks:paranamer:2.2.1:*:*:*:*:*:*:*"},{"name":"syft:cpe23","value":"cpe:2.3:a:paranamer:paranamer:2.2.1:*:*:*:*:*:*:*"},{"name":"syft:location:0:path","value":"\\example\\jdonMVC+CQRS+ES\\pom.xml"},{"name":"syft:metadata:-:artifactID","value":"paranamer"},{"name":"syft:metadata:-:groupID","value":"com.thoughtworks.paranamer"}]},{"bom-ref":"pkg:maven/org.picocontainer/picocontainer@1.2?package-id=58c177f9121eda58","type":"library","group":"org.picocontainer","name":"picocontainer","version":"1.2","licenses":[{"license":{"name":"http://www.picocontainer.org/License","url":"http://www.picocontainer.org/License"}}],"cpe":"cpe:2.3:a:org.picocontainer:picocontainer:1.2:*:*:*:*:*:*:*","purl":"pkg:maven/org.picocontainer/picocontainer@1.2","externalReferences":[{"url":"","hashes":[{"alg":"SHA-1","content":"a23b03f347bb9fab74b5120eb18d0eb07c115fde"}],"type":"build-meta"}],"properties":[{"name":"syft:package:foundBy","value":"java-archive-cataloger"},{"name":"syft:package:language","value":"java"},{"name":"syft:package:type","value":"java-archive"},{"name":"syft:package:metadataType","value":"java-archive"},{"name":"syft:cpe23","value":"cpe:2.3:a:picocontainer:picocontainer:1.2:*:*:*:*:*:*:*"},{"name":"syft:cpe23","value":"cpe:2.3:a:codehaus:picocontainer:1.2:*:*:*:*:*:*:*"},{"name":"syft:location:0:path","value":"\\example\\cargo\\lib\\picocontainer-1.2.jar"},{"name":"syft:metadata:-:artifactID","value":"picocontainer"},{"name":"syft:metadata:-:groupID","value":"org.picocontainer"},{"name":"syft:metadata:virtualPath","value":"\\example\\cargo\\lib\\picocontainer-1.2.jar"}]},{"bom-ref":"pkg:maven/org.picocontainer/picocontainer@1.2?package-id=d1ee071ca5ac9a39","type":"library","group":"org.picocontainer","name":"picocontainer","version":"1.2","cpe":"cpe:2.3:a:org.picocontainer:picocontainer:1.2:*:*:*:*:*:*:*","purl":"pkg:maven/org.picocontainer/picocontainer@1.2","properties":[{"name":"syft:package:foundBy","value":"java-pom-cataloger"},{"name":"syft:package:language","value":"java"},{"name":"syft:package:type","value":"java-archive"},{"name":"syft:package:metadataType","value":"java-archive"},{"name":"syft:cpe23","value":"cpe:2.3:a:picocontainer:picocontainer:1.2:*:*:*:*:*:*:*"},{"name":"syft:location:0:path","value":"\\pom.xml"},{"name":"syft:metadata:-:artifactID","value":"picocontainer"},{"name":"syft:metadata:-:groupID","value":"org.picocontainer"}]},{"bom-ref":"pkg:maven/regexp/regexp@1.2?package-id=c09183a3849e5f9d","type":"library","group":"regexp","name":"regexp","version":"1.2","cpe":"cpe:2.3:a:regexp:regexp:1.2:*:*:*:*:*:*:*","purl":"pkg:maven/regexp/regexp@1.2","properties":[{"name":"syft:package:foundBy","value":"java-pom-cataloger"},{"name":"syft:package:language","value":"java"},{"name":"syft:package:type","value":"java-archive"},{"name":"syft:package:metadataType","value":"java-archive"},{"name":"syft:location:0:path","value":"\\pom.xml"},{"name":"syft:metadata:-:artifactID","value":"regexp"},{"name":"syft:metadata:-:groupID","value":"regexp"}]},{"bom-ref":"pkg:maven/sample/robot@1.0-SNAPSHOT?package-id=09f5542da98ad017","type":"library","name":"robot","version":"1.0-SNAPSHOT","cpe":"cpe:2.3:a:robot:robot:1.0-SNAPSHOT:*:*:*:*:*:*:*","purl":"pkg:maven/sample/robot@1.0-SNAPSHOT","properties":[{"name":"syft:package:foundBy","value":"java-pom-cataloger"},{"name":"syft:package:language","value":"java"},{"name":"syft:package:type","value":"java-archive"},{"name":"syft:package:metadataType","value":"java-archive"},{"name":"syft:location:0:path","value":"\\example\\cqrs+dci\\robot\\pom.xml"}]},{"bom-ref":"pkg:maven/org.scannotation/scannotation@1.0.2?package-id=cacb764b9bb245fb","type":"library","group":"org.scannotation","name":"scannotation","version":"1.0.2","cpe":"cpe:2.3:a:org.scannotation:scannotation:1.0.2:*:*:*:*:*:*:*","purl":"pkg:maven/org.scannotation/scannotation@1.0.2","externalReferences":[{"url":"","hashes":[{"alg":"SHA-1","content":"efd5626f436eab1f3f578cbd8c25dd0e7b7a46ef"}],"type":"build-meta"}],"properties":[{"name":"syft:package:foundBy","value":"java-archive-cataloger"},{"name":"syft:package:language","value":"java"},{"name":"syft:package:type","value":"java-archive"},{"name":"syft:package:metadataType","value":"java-archive"},{"name":"syft:cpe23","value":"cpe:2.3:a:scannotation:scannotation:1.0.2:*:*:*:*:*:*:*"},{"name":"syft:location:0:path","value":"\\example\\cargo\\lib\\scannotation-1.0.2.jar"},{"name":"syft:metadata:-:artifactID","value":"scannotation"},{"name":"syft:metadata:-:groupID","value":"org.scannotation"},{"name":"syft:metadata:virtualPath","value":"\\example\\cargo\\lib\\scannotation-1.0.2.jar"}]},{"bom-ref":"pkg:maven/net.sf.scannotation/scannotation@1.0.2?package-id=f475fdb08842069e","type":"library","group":"net.sf.scannotation","name":"scannotation","version":"1.0.2","cpe":"cpe:2.3:a:net.sf.scannotation:scannotation:1.0.2:*:*:*:*:*:*:*","purl":"pkg:maven/net.sf.scannotation/scannotation@1.0.2","properties":[{"name":"syft:package:foundBy","value":"java-pom-cataloger"},{"name":"syft:package:language","value":"java"},{"name":"syft:package:type","value":"java-archive"},{"name":"syft:package:metadataType","value":"java-archive"},{"name":"syft:cpe23","value":"cpe:2.3:a:scannotation:scannotation:1.0.2:*:*:*:*:*:*:*"},{"name":"syft:cpe23","value":"cpe:2.3:a:sf:scannotation:1.0.2:*:*:*:*:*:*:*"},{"name":"syft:location:0:path","value":"\\example\\jdonMVC+CQRS+ES\\pom.xml"},{"name":"syft:metadata:-:artifactID","value":"scannotation"},{"name":"syft:metadata:-:groupID","value":"net.sf.scannotation"}]},{"bom-ref":"pkg:maven/javax.servlet/servlet-api@2.5?package-id=c2a467e306df20ee","type":"library","group":"javax.servlet","name":"servlet-api","version":"2.5","cpe":"cpe:2.3:a:servlet-api:servlet-api:2.5:*:*:*:*:*:*:*","purl":"pkg:maven/javax.servlet/servlet-api@2.5","properties":[{"name":"syft:package:foundBy","value":"java-pom-cataloger"},{"name":"syft:package:language","value":"java"},{"name":"syft:package:type","value":"java-archive"},{"name":"syft:package:metadataType","value":"java-archive"},{"name":"syft:cpe23","value":"cpe:2.3:a:servlet-api:servlet_api:2.5:*:*:*:*:*:*:*"},{"name":"syft:cpe23","value":"cpe:2.3:a:servlet_api:servlet-api:2.5:*:*:*:*:*:*:*"},{"name":"syft:cpe23","value":"cpe:2.3:a:servlet_api:servlet_api:2.5:*:*:*:*:*:*:*"},{"name":"syft:cpe23","value":"cpe:2.3:a:servlet:servlet-api:2.5:*:*:*:*:*:*:*"},{"name":"syft:cpe23","value":"cpe:2.3:a:servlet:servlet_api:2.5:*:*:*:*:*:*:*"},{"name":"syft:location:0:path","value":"\\JdonAccessory\\jdon-remote\\pom.xml"},{"name":"syft:metadata:-:artifactID","value":"servlet-api"},{"name":"syft:metadata:-:groupID","value":"javax.servlet"}]},{"bom-ref":"pkg:maven/servlet-api/servlet-api?package-id=7f1ecac2a63b4cbf","type":"library","name":"servlet-api","version":"UNKNOWN","cpe":"cpe:2.3:a:servlet-api:servlet-api:*:*:*:*:*:*:*:*","purl":"pkg:maven/servlet-api/servlet-api","externalReferences":[{"url":"","hashes":[{"alg":"SHA-1","content":"413720782508cfb3441c4b8d625c172a2364a994"}],"type":"build-meta"}],"properties":[{"name":"syft:package:foundBy","value":"java-archive-cataloger"},{"name":"syft:package:language","value":"java"},{"name":"syft:package:type","value":"java-archive"},{"name":"syft:package:metadataType","value":"java-archive"},{"name":"syft:cpe23","value":"cpe:2.3:a:servlet-api:servlet_api:*:*:*:*:*:*:*:*"},{"name":"syft:cpe23","value":"cpe:2.3:a:servlet_api:servlet-api:*:*:*:*:*:*:*:*"},{"name":"syft:cpe23","value":"cpe:2.3:a:servlet_api:servlet_api:*:*:*:*:*:*:*:*"},{"name":"syft:cpe23","value":"cpe:2.3:a:servlet:servlet-api:*:*:*:*:*:*:*:*"},{"name":"syft:cpe23","value":"cpe:2.3:a:servlet:servlet_api:*:*:*:*:*:*:*:*"},{"name":"syft:location:0:path","value":"\\example\\cargo\\lib\\servlet-api.jar"},{"name":"syft:metadata:virtualPath","value":"\\example\\cargo\\lib\\servlet-api.jar"}]},{"bom-ref":"pkg:maven/struts/struts@1.2.9?package-id=fe5b5ad8f1dd4518","type":"library","group":"struts","name":"struts","version":"1.2.9","cpe":"cpe:2.3:a:struts:struts:1.2.9:*:*:*:*:*:*:*","purl":"pkg:maven/struts/struts@1.2.9","properties":[{"name":"syft:package:foundBy","value":"java-pom-cataloger"},{"name":"syft:package:language","value":"java"},{"name":"syft:package:type","value":"java-archive"},{"name":"syft:package:metadataType","value":"java-archive"},{"name":"syft:location:0:path","value":"\\JdonAccessory\\jdon-hibernate3x\\pom.xml"},{"name":"syft:metadata:-:artifactID","value":"struts"},{"name":"syft:metadata:-:groupID","value":"struts"}]},{"bom-ref":"pkg:maven/sample/testWeb@1.0-SNAPSHOT?package-id=40982d68007442a1","type":"library","name":"testWeb","version":"1.0-SNAPSHOT","cpe":"cpe:2.3:a:testWeb:testWeb:1.0-SNAPSHOT:*:*:*:*:*:*:*","purl":"pkg:maven/sample/testWeb@1.0-SNAPSHOT","properties":[{"name":"syft:package:foundBy","value":"java-pom-cataloger"},{"name":"syft:package:language","value":"java"},{"name":"syft:package:type","value":"java-archive"},{"name":"syft:package:metadataType","value":"java-archive"},{"name":"syft:location:0:path","value":"\\doc\\english\\pom.xml"}]},{"bom-ref":"pkg:maven/org.apache.velocity/velocity@1.6.4?package-id=d42af46c360ebd3d","type":"library","group":"org.apache.velocity","name":"velocity","version":"1.6.4","cpe":"cpe:2.3:a:apache:velocity:1.6.4:*:*:*:*:*:*:*","purl":"pkg:maven/org.apache.velocity/velocity@1.6.4","properties":[{"name":"syft:package:foundBy","value":"java-pom-cataloger"},{"name":"syft:package:language","value":"java"},{"name":"syft:package:type","value":"java-archive"},{"name":"syft:package:metadataType","value":"java-archive"},{"name":"syft:location:0:path","value":"\\example\\jdonMVC+CQRS+ES\\pom.xml"},{"name":"syft:metadata:-:artifactID","value":"velocity"},{"name":"syft:metadata:-:groupID","value":"org.apache.velocity"}]}],"dependencies":[{"ref":"pkg:maven/com.jdon/jdonmvc_cqrs_es@1.0?package-id=e0a2954c8ee06bc9","dependsOn":["pkg:maven/com.jdon.mvc/jdonmvc-core@1.0-SNAPSHOT?package-id=11f08e6a0173854a","pkg:maven/com.jdon/jdon-jdbc@6.6.4?package-id=7de7fb3b5d85abe0","pkg:maven/com.thoughtworks.paranamer/paranamer@2.2.1?package-id=e46b1a9ebe34287f","pkg:maven/commons-beanutils/commons-beanutils@1.8.3?package-id=5f175b492c4ce13b","pkg:maven/commons-fileupload/commons-fileupload@1.2.2?package-id=729daa6dfde0e281","pkg:maven/commons-logging/commons-logging@1.1.1?package-id=131de380abb2c5cf","pkg:maven/commons-pool/commons-pool@1.6?package-id=610cee33174f21fc","pkg:maven/freemarker/freemarker@2.3.8?package-id=c2bf22f3c2ec5934","pkg:maven/javax.servlet/servlet-api@2.5?package-id=c2a467e306df20ee","pkg:maven/javax.ws.rs/jsr311-api@1.1.1?package-id=8f6ea7a852c8f205","pkg:maven/jstl/jstl@1.2?package-id=23bfee3a2711adc7","pkg:maven/junit/junit@3.8.1?package-id=e2199aa12519ad9a","pkg:maven/log4j/log4j@1.2.4?package-id=78c5c2f8c68c35f2","pkg:maven/net.sf.scannotation/scannotation@1.0.2?package-id=f475fdb08842069e","pkg:maven/org.apache.commons/commons-io@1.3.2?package-id=807092dd4b0394f6","pkg:maven/org.apache.velocity/velocity@1.6.4?package-id=d42af46c360ebd3d","pkg:maven/org.commontemplate/commontemplate@0.8.7?package-id=ab2c0ef5b5060487","pkg:maven/org.jdon/jdonframework@6.9?package-id=59c90396b7e2c2fa"]},{"ref":"pkg:maven/org.jdon/jdon-hibernate3x@6.6.4?package-id=4c4284c062d55234","dependsOn":["pkg:maven/com.jdon/jdonJ2EE@6.6.4?package-id=d5403c1753bd80d4","pkg:maven/jdom/jdom@1.0?package-id=14abf15ec06f3b49","pkg:maven/junit/junit@3.8.1?package-id=e2199aa12519ad9a","pkg:maven/org.apache.logging.log4j/log4j2@2.0?package-id=bbfec24abe8645d8","pkg:maven/org.apache.tomcat/jsp-api@6.0.37?package-id=474468ca88938657","pkg:maven/org.jdon/jdonframework@6.6.4?package-id=762643f6c5e12007","pkg:maven/struts/struts@1.2.9?package-id=fe5b5ad8f1dd4518"]},{"ref":"pkg:maven/org.jdon/jdon-jdbc@6.6.4?package-id=63095f4021d871b6","dependsOn":["pkg:maven/junit/junit@3.8.1?package-id=e2199aa12519ad9a","pkg:maven/org.apache.logging.log4j/log4j2@2.0?package-id=bbfec24abe8645d8","pkg:maven/org.jdon/jdonframework@6.6.4?package-id=762643f6c5e12007"]},{"ref":"pkg:maven/org.jdon/jdon-remote@6.6.4?package-id=886c57dc392f2309","dependsOn":["pkg:maven/com.jdon/jdonJ2EE@6.6.4?package-id=d5403c1753bd80d4","pkg:maven/javax.servlet/servlet-api@2.5?package-id=c2a467e306df20ee","pkg:maven/junit/junit@3.8.1?package-id=e2199aa12519ad9a","pkg:maven/org.apache.logging.log4j/log4j2@2.0?package-id=bbfec24abe8645d8","pkg:maven/org.apache.tomcat/jsp-api@6.0.37?package-id=474468ca88938657","pkg:maven/org.jdon/jdonframework@6.6.4?package-id=762643f6c5e12007"]},{"ref":"pkg:maven/org.jdon/jdon-struts1x@6.6.4?package-id=a77f1b6e0337129e","dependsOn":["pkg:maven/com.jdon/jdonJ2EE@6.6.4?package-id=d5403c1753bd80d4","pkg:maven/javax.servlet/servlet-api@2.5?package-id=c2a467e306df20ee","pkg:maven/jdom/jdom@1.0?package-id=14abf15ec06f3b49","pkg:maven/junit/junit@3.8.1?package-id=e2199aa12519ad9a","pkg:maven/org.apache.logging.log4j/log4j2@2.0?package-id=bbfec24abe8645d8","pkg:maven/org.apache.tomcat/jsp-api@6.0.37?package-id=474468ca88938657","pkg:maven/org.jdon/jdonframework@6.6.4?package-id=762643f6c5e12007","pkg:maven/struts/struts@1.2.9?package-id=fe5b5ad8f1dd4518"]},{"ref":"pkg:maven/org.jdon/jdonframework@6.9?package-id=59c90396b7e2c2fa","dependsOn":["pkg:maven/aopalliance/aopalliance@1.0?package-id=2c98841528b61609","pkg:maven/cglib/cglib@2.2.2?package-id=1d8759a71cabdc61","pkg:maven/com.google.guava/guava@23.0?package-id=a57443ee8defe627","pkg:maven/com.lmax/disruptor@3.3.8?package-id=36812b404a8a534a","pkg:maven/commons-pool/commons-pool@1.6?package-id=610cee33174f21fc","pkg:maven/javax.servlet/servlet-api@2.5?package-id=c2a467e306df20ee","pkg:maven/jdom/jdom@1.0?package-id=14abf15ec06f3b49","pkg:maven/junit/junit@3.8.1?package-id=e2199aa12519ad9a","pkg:maven/net.sf.scannotation/scannotation@1.0.2?package-id=f475fdb08842069e","pkg:maven/org.apache.logging.log4j/log4j-api@2.11.0?package-id=ab4696285722e9d9","pkg:maven/org.apache.logging.log4j/log4j-core@2.11.0?package-id=6400a51f631fe60c","pkg:maven/org.javassist/javassist@3.23.1-GA?package-id=275e430d9b8ec171","pkg:maven/org.picocontainer/picocontainer@1.2?package-id=d1ee071ca5ac9a39","pkg:maven/regexp/regexp@1.2?package-id=c09183a3849e5f9d"]},{"ref":"pkg:maven/sample/dciderobot@1.0-SNAPSHOT?package-id=c767a110c900f67c","dependsOn":["pkg:maven/commons-pool/commons-pool@1.6?package-id=610cee33174f21fc","pkg:maven/javax.servlet/servlet-api@2.5?package-id=c2a467e306df20ee","pkg:maven/junit/junit@3.8.1?package-id=e2199aa12519ad9a","pkg:maven/org.jdon/jdonframework@6.9?package-id=59c90396b7e2c2fa"]},{"ref":"pkg:maven/sample/match@1.0-SNAPSHOT?package-id=8ac5b599b9c0cdc4","dependsOn":["pkg:maven/commons-pool/commons-pool@1.6?package-id=610cee33174f21fc","pkg:maven/javax.servlet/servlet-api@2.5?package-id=c2a467e306df20ee","pkg:maven/junit/junit@3.8.1?package-id=e2199aa12519ad9a","pkg:maven/org.jdon/jdonframework@6.9?package-id=59c90396b7e2c2fa"]},{"ref":"pkg:maven/sample/robot@1.0-SNAPSHOT?package-id=09f5542da98ad017","dependsOn":["pkg:maven/commons-pool/commons-pool@1.6?package-id=610cee33174f21fc","pkg:maven/javax.servlet/servlet-api@2.5?package-id=c2a467e306df20ee","pkg:maven/junit/junit@3.8.1?package-id=e2199aa12519ad9a","pkg:maven/org.jdon/jdonframework@6.9?package-id=59c90396b7e2c2fa"]},{"ref":"pkg:maven/sample/testWeb@1.0-SNAPSHOT?package-id=40982d68007442a1","dependsOn":["pkg:maven/com.jdon/jdon-jdbc@6.6.4?package-id=7de7fb3b5d85abe0","pkg:maven/com.jdon/jdon-struts1x@6.6.4?package-id=dd500831ccd70f85","pkg:maven/javax.servlet/servlet-api@2.5?package-id=c2a467e306df20ee","pkg:maven/junit/junit@3.8.1?package-id=e2199aa12519ad9a","pkg:maven/log4j/log4j@1.2.4?package-id=78c5c2f8c68c35f2","pkg:maven/org.jdon/jdonframework@6.6.4?package-id=762643f6c5e12007","pkg:maven/struts/struts@1.2.9?package-id=fe5b5ad8f1dd4518"]}]}
