{"$schema":"http://cyclonedx.org/schema/bom-1.6.schema.json","bomFormat":"CycloneDX","specVersion":"1.6","serialNumber":"urn:uuid:de07d995-5f0f-4dc0-ab43-c93b88f012f1","version":1,"metadata":{"timestamp":"2026-04-20T19:05:50+02:00","tools":{"components":[{"type":"application","author":"anchore","name":"syft","version":"1.42.1"}]},"component":{"bom-ref":"9b0824931cd8d262","type":"file","name":"D:\\TFG\\Proyectosquesbomear\\nlp-lang-master\\nlp-lang-master"}},"components":[{"bom-ref":"pkg:maven/commons-logging/commons-logging@1.2?package-id=f30433814515d4e8","type":"library","group":"commons-logging","name":"commons-logging","version":"1.2","cpe":"cpe:2.3:a:commons-logging:commons-logging:1.2:*:*:*:*:*:*:*","purl":"pkg:maven/commons-logging/commons-logging@1.2","properties":[{"name":"syft:package:foundBy","value":"java-pom-cataloger"},{"name":"syft:package:language","value":"java"},{"name":"syft:package:type","value":"java-archive"},{"name":"syft:package:metadataType","value":"java-archive"},{"name":"syft:cpe23","value":"cpe:2.3:a:commons-logging:commons_logging:1.2:*:*:*:*:*:*:*"},{"name":"syft:cpe23","value":"cpe:2.3:a:commons_logging:commons-logging:1.2:*:*:*:*:*:*:*"},{"name":"syft:cpe23","value":"cpe:2.3:a:commons_logging:commons_logging:1.2:*:*:*:*:*:*:*"},{"name":"syft:cpe23","value":"cpe:2.3:a:commons:commons-logging:1.2:*:*:*:*:*:*:*"},{"name":"syft:cpe23","value":"cpe:2.3:a:commons:commons_logging:1.2:*:*:*:*:*:*:*"},{"name":"syft:location:0:path","value":"\\pom.xml"},{"name":"syft:metadata:-:artifactID","value":"commons-logging"},{"name":"syft:metadata:-:groupID","value":"commons-logging"}]},{"bom-ref":"pkg:maven/junit/junit@4.13.1?package-id=063c28e20d2d907b","type":"library","group":"junit","name":"junit","version":"4.13.1","cpe":"cpe:2.3:a:junit:junit:4.13.1:*:*:*:*:*:*:*","purl":"pkg:maven/junit/junit@4.13.1","properties":[{"name":"syft:package:foundBy","value":"java-pom-cataloger"},{"name":"syft:package:language","value":"java"},{"name":"syft:package:type","value":"java-archive"},{"name":"syft:package:metadataType","value":"java-archive"},{"name":"syft:location:0:path","value":"\\pom.xml"},{"name":"syft:metadata:-:artifactID","value":"junit"},{"name":"syft:metadata:-:groupID","value":"junit"}]},{"bom-ref":"pkg:maven/log4j/log4j@1.2.17?package-id=de1372ea15fada99","type":"library","group":"log4j","name":"log4j","version":"1.2.17","cpe":"cpe:2.3:a:apache:log4j:1.2.17:*:*:*:*:*:*:*","purl":"pkg:maven/log4j/log4j@1.2.17","properties":[{"name":"syft:package:foundBy","value":"java-pom-cataloger"},{"name":"syft:package:language","value":"java"},{"name":"syft:package:type","value":"java-archive"},{"name":"syft:package:metadataType","value":"java-archive"},{"name":"syft:location:0:path","value":"\\pom.xml"},{"name":"syft:metadata:-:artifactID","value":"log4j"},{"name":"syft:metadata:-:groupID","value":"log4j"}]},{"bom-ref":"pkg:maven/org.apache.logging.log4j/log4j-api@2.17.1?package-id=4e15de9583caecc4","type":"library","group":"org.apache.logging.log4j","name":"log4j-api","version":"2.17.1","cpe":"cpe:2.3:a:apache:log4j-api:2.17.1:*:*:*:*:*:*:*","purl":"pkg:maven/org.apache.logging.log4j/log4j-api@2.17.1","properties":[{"name":"syft:package:foundBy","value":"java-pom-cataloger"},{"name":"syft:package:language","value":"java"},{"name":"syft:package:type","value":"java-archive"},{"name":"syft:package:metadataType","value":"java-archive"},{"name":"syft:cpe23","value":"cpe:2.3:a:apache:log4j_api:2.17.1:*:*:*:*:*:*:*"},{"name":"syft:cpe23","value":"cpe:2.3:a:apache:log4j:2.17.1:*:*:*:*:*:*:*"},{"name":"syft:location:0:path","value":"\\pom.xml"},{"name":"syft:metadata:-:artifactID","value":"log4j-api"},{"name":"syft:metadata:-:groupID","value":"org.apache.logging.log4j"}]},{"bom-ref":"pkg:maven/org.nlpcn/nlp-lang@1.7.9?package-id=6bdb8a297ef06dd5","type":"library","name":"nlp-lang","version":"1.7.9","licenses":[{"license":{"name":"The Apache Software License, Version 2.0","url":"http://www.apache.org/licenses/LICENSE-2.0.txt"}}],"cpe":"cpe:2.3:a:org.nlpcn:nlp-lang:1.7.9:*:*:*:*:*:*:*","purl":"pkg:maven/org.nlpcn/nlp-lang@1.7.9","properties":[{"name":"syft:package:foundBy","value":"java-pom-cataloger"},{"name":"syft:package:language","value":"java"},{"name":"syft:package:type","value":"java-archive"},{"name":"syft:package:metadataType","value":"java-archive"},{"name":"syft:cpe23","value":"cpe:2.3:a:org.nlpcn:nlp_lang:1.7.9:*:*:*:*:*:*:*"},{"name":"syft:cpe23","value":"cpe:2.3:a:nlp-lang:nlp-lang:1.7.9:*:*:*:*:*:*:*"},{"name":"syft:cpe23","value":"cpe:2.3:a:nlp-lang:nlp_lang:1.7.9:*:*:*:*:*:*:*"},{"name":"syft:cpe23","value":"cpe:2.3:a:nlp_lang:nlp-lang:1.7.9:*:*:*:*:*:*:*"},{"name":"syft:cpe23","value":"cpe:2.3:a:nlp_lang:nlp_lang:1.7.9:*:*:*:*:*:*:*"},{"name":"syft:cpe23","value":"cpe:2.3:a:nlpcn:nlp-lang:1.7.9:*:*:*:*:*:*:*"},{"name":"syft:cpe23","value":"cpe:2.3:a:nlpcn:nlp_lang:1.7.9:*:*:*:*:*:*:*"},{"name":"syft:cpe23","value":"cpe:2.3:a:nlp:nlp-lang:1.7.9:*:*:*:*:*:*:*"},{"name":"syft:cpe23","value":"cpe:2.3:a:nlp:nlp_lang:1.7.9:*:*:*:*:*:*:*"},{"name":"syft:location:0:path","value":"\\pom.xml"}]},{"bom-ref":"pkg:maven/org.slf4j/slf4j-api@1.7.7?package-id=a8870f35c138876f","type":"library","group":"org.slf4j","name":"slf4j-api","version":"1.7.7","cpe":"cpe:2.3:a:org.slf4j:slf4j-api:1.7.7:*:*:*:*:*:*:*","purl":"pkg:maven/org.slf4j/slf4j-api@1.7.7","properties":[{"name":"syft:package:foundBy","value":"java-pom-cataloger"},{"name":"syft:package:language","value":"java"},{"name":"syft:package:type","value":"java-archive"},{"name":"syft:package:metadataType","value":"java-archive"},{"name":"syft:cpe23","value":"cpe:2.3:a:org.slf4j:slf4j_api:1.7.7:*:*:*:*:*:*:*"},{"name":"syft:cpe23","value":"cpe:2.3:a:slf4j-api:slf4j-api:1.7.7:*:*:*:*:*:*:*"},{"name":"syft:cpe23","value":"cpe:2.3:a:slf4j-api:slf4j_api:1.7.7:*:*:*:*:*:*:*"},{"name":"syft:cpe23","value":"cpe:2.3:a:slf4j_api:slf4j-api:1.7.7:*:*:*:*:*:*:*"},{"name":"syft:cpe23","value":"cpe:2.3:a:slf4j_api:slf4j_api:1.7.7:*:*:*:*:*:*:*"},{"name":"syft:cpe23","value":"cpe:2.3:a:slf4j:slf4j-api:1.7.7:*:*:*:*:*:*:*"},{"name":"syft:cpe23","value":"cpe:2.3:a:slf4j:slf4j_api:1.7.7:*:*:*:*:*:*:*"},{"name":"syft:location:0:path","value":"\\pom.xml"},{"name":"syft:metadata:-:artifactID","value":"slf4j-api"},{"name":"syft:metadata:-:groupID","value":"org.slf4j"}]}],"dependencies":[{"ref":"pkg:maven/org.nlpcn/nlp-lang@1.7.9?package-id=6bdb8a297ef06dd5","dependsOn":["pkg:maven/commons-logging/commons-logging@1.2?package-id=f30433814515d4e8","pkg:maven/junit/junit@4.13.1?package-id=063c28e20d2d907b","pkg:maven/log4j/log4j@1.2.17?package-id=de1372ea15fada99","pkg:maven/org.apache.logging.log4j/log4j-api@2.17.1?package-id=4e15de9583caecc4","pkg:maven/org.slf4j/slf4j-api@1.7.7?package-id=a8870f35c138876f"]}]}
